[{"member":"(Nigel) Vaz","dim1":0.109,"dim2":-0.0101,"party":"Labour"},{"member":"Adam Afriyie","dim1":-19.8692,"dim2":2.1296,"party":"Conservative"},{"member":"Adam Holloway","dim1":-17.1184,"dim2":1.6742,"party":"Conservative"},{"member":"Adrian Bailey","dim1":0.2384,"dim2":-0.1093,"party":"Labour"},{"member":"Adrian Sanders","dim1":-0.1609,"dim2":0.1565,"party":"Liberal Democrat"},{"member":"Afzal Khan","dim1":9.3415,"dim2":9.2989,"party":"Labour"},{"member":"Aidan Burley","dim1":-0.0996,"dim2":0.1027,"party":"Conservative"},{"member":"Alan Beith","dim1":-0.183,"dim2":0.1521,"party":"Liberal Democrat"},{"member":"Alan Brown","dim1":15.1448,"dim2":0.6935,"party":"Scottish National Party"},{"member":"Alan Campbell","dim1":0.2384,"dim2":-0.1093,"party":"Labour"},{"member":"Alan Duncan","dim1":-0.1896,"dim2":0.1561,"party":"Conservative"},{"member":"Alan Haselhurst","dim1":-0.2219,"dim2":0.1713,"party":"Conservative"},{"member":"Alan Johnson","dim1":5.9107,"dim2":-4.5827,"party":"Labour"},{"member":"Alan Mak","dim1":-10.7906,"dim2":-7.8854,"party":"Conservative"},{"member":"Alan Reid","dim1":-0.183,"dim2":0.1521,"party":"Liberal Democrat"},{"member":"Alan Whitehead","dim1":0.2384,"dim2":-0.1093,"party":"Labour"},{"member":"Alasdair McDonnell","dim1":0.1953,"dim2":-0.0772,"party":"Social Democratic & Labour Party"},{"member":"Albert Owen","dim1":15.6941,"dim2":2.515,"party":"Labour"},{"member":"Alberto Costa","dim1":-19.6173,"dim2":1.836,"party":"Conservative"},{"member":"Alec Shelbrooke","dim1":-18.7791,"dim2":1.6778,"party":"Conservative"},{"member":"Alex Burghart","dim1":-10.5594,"dim2":-8.1137,"party":"Conservative"},{"member":"Alex Chalk","dim1":-19.7608,"dim2":2.0819,"party":"Conservative"},{"member":"Alex Cunningham","dim1":17.479,"dim2":2.3849,"party":"Labour"},{"member":"Alex Norris","dim1":9.3051,"dim2":9.28,"party":"Labour"},{"member":"Alex Salmond","dim1":3.5188,"dim2":-3.9306,"party":"Scottish National Party"},{"member":"Alex Sobel","dim1":9.0921,"dim2":8.4322,"party":"Labour"},{"member":"Alexander Beresford","dim1":-0.0685,"dim2":0.0597,"party":"Conservative"},{"member":"Alexander Randall","dim1":-0.1421,"dim2":0.1262,"party":"Conservative"},{"member":"Alison McGovern","dim1":16.0324,"dim2":2.7075,"party":"Labour"},{"member":"Alison Seabeck","dim1":0.2384,"dim2":-0.1093,"party":"Labour"},{"member":"Alison Thewliss","dim1":15.4346,"dim2":-0.1078,"party":"Scottish National Party"},{"member":"Alistair Burt","dim1":-19.3408,"dim2":2.334,"party":"Conservative"},{"member":"Alistair Carmichael","dim1":-0.1998,"dim2":0.1758,"party":"Liberal Democrat"},{"member":"Alistair Darling","dim1":0.2384,"dim2":-0.1093,"party":"Labour"},{"member":"Alok Sharma","dim1":-20.1009,"dim2":2.0911,"party":"Conservative"},{"member":"Alun Cairns","dim1":-18.7624,"dim2":0.8581,"party":"Conservative"},{"member":"Amanda Milling","dim1":-19.0513,"dim2":3.0904,"party":"Conservative"},{"member":"Amanda Solloway","dim1":-9.68,"dim2":10.5679,"party":"Conservative"},{"member":"Amber Rudd","dim1":-19.6163,"dim2":1.8918,"party":"Conservative"},{"member":"Anas Sarwar","dim1":0.2384,"dim2":-0.1093,"party":"Labour"},{"member":"Andrea Jenkyns","dim1":-15.516,"dim2":4.4589,"party":"Conservative"},{"member":"Andrea Leadsom","dim1":-18.5195,"dim2":1.3095,"party":"Conservative"},{"member":"Andrew Bingham","dim1":-9.547,"dim2":10.4398,"party":"Conservative"},{"member":"Andrew Bowie","dim1":-10.5953,"dim2":-8.1281,"party":"Conservative"},{"member":"Andrew Bridgen","dim1":-20.1286,"dim2":2.2646,"party":"Conservative"},{"member":"Andrew Burnham","dim1":0.2384,"dim2":-0.1093,"party":"Labour"},{"member":"Andrew George","dim1":-0.1199,"dim2":0.1331,"party":"Liberal Democrat"},{"member":"Andrew Griffiths","dim1":-18.4526,"dim2":2.3516,"party":"Conservative"},{"member":"Andrew Gwynne","dim1":15.1698,"dim2":3.4876,"party":"Labour"},{"member":"Andrew Jones","dim1":-20.2216,"dim2":2.9309,"party":"Conservative"},{"member":"Andrew Lansley","dim1":-0.0483,"dim2":0.064,"party":"Conservative"},{"member":"Andrew Lewer","dim1":-10.5706,"dim2":-8.1111,"party":"Conservative"},{"member":"Andrew Love","dim1":0.2384,"dim2":-0.1093,"party":"Labour"},{"member":"Andrew McDonald","dim1":0.2384,"dim2":-0.1093,"party":"Labour"},{"member":"Andrew Miller","dim1":0.2384,"dim2":-0.1093,"party":"Labour"},{"member":"Andrew Mitchell","dim1":-0.1401,"dim2":0.1287,"party":"Conservative"},{"member":"Andrew Murrison","dim1":-0.2528,"dim2":0.1751,"party":"Conservative"},{"member":"Andrew Percy","dim1":-19.7509,"dim2":2.2338,"party":"Conservative"},{"member":"Andrew Robathan","dim1":-0.183,"dim2":0.1521,"party":"Conservative"},{"member":"Andrew Rosindell","dim1":-18.6873,"dim2":2.1721,"party":"Conservative"},{"member":"Andrew Selous","dim1":-20.1714,"dim2":2.789,"party":"Conservative"},{"member":"Andrew Slaughter","dim1":0.2384,"dim2":-0.1093,"party":"Labour"},{"member":"Andrew Smith","dim1":0.109,"dim2":-0.0101,"party":"Labour"},{"member":"Andrew Stephenson","dim1":-17.2431,"dim2":3.1614,"party":"Conservative"},{"member":"Andrew Turner","dim1":-0.2219,"dim2":0.1713,"party":"Conservative"},{"member":"Andrew Tyrie","dim1":-0.1998,"dim2":0.1758,"party":"Conservative"},{"member":"Andy Burnham","dim1":4.4212,"dim2":-3.3717,"party":"Labour"},{"member":"Andy McDonald","dim1":16.568,"dim2":3.0067,"party":"Labour"},{"member":"Andy Sawford","dim1":0.2384,"dim2":-0.1093,"party":"Labour"},{"member":"Andy Slaughter","dim1":17.18,"dim2":2.2054,"party":"Labour"},{"member":"Angela Crawley","dim1":12.5152,"dim2":-0.4269,"party":"Scottish National Party"},{"member":"Angela Eagle","dim1":0.2384,"dim2":-0.1093,"party":"Labour"},{"member":"Angela Rayner","dim1":15.879,"dim2":1.799,"party":"Labour"},{"member":"Angela Smith","dim1":16.2435,"dim2":1.8794,"party":"Labour"},{"member":"Angela Watkinson","dim1":-0.1115,"dim2":0.083,"party":"Conservative"},{"member":"Angie Bray","dim1":-0.0894,"dim2":0.0875,"party":"Conservative"},{"member":"Angus Brendan MacNeil","dim1":12.9023,"dim2":-0.4914,"party":"Scottish National Party"},{"member":"Angus MacNeil","dim1":0.2384,"dim2":-0.1093,"party":"Scottish National"},{"member":"Angus Robertson","dim1":6.2211,"dim2":-6.7445,"party":"Scottish National Party"},{"member":"Ann Clwyd","dim1":13.6116,"dim2":1.3264,"party":"Labour"},{"member":"Ann Coffey","dim1":14.2457,"dim2":1.5894,"party":"Labour"},{"member":"Ann McKechin","dim1":0.2384,"dim2":-0.1093,"party":"Labour"},{"member":"Anna McMorrin","dim1":8.966,"dim2":8.8193,"party":"Labour"},{"member":"Anna Soubry","dim1":-16.2557,"dim2":4.8163,"party":"Conservative"},{"member":"Anna Turley","dim1":13.0149,"dim2":-0.3292,"party":"Labour"},{"member":"Anne Main","dim1":-0.1384,"dim2":0.1244,"party":"Conservative"},{"member":"Anne Marie Morris","dim1":-19.4525,"dim2":2.4264,"party":"Conservative"},{"member":"Anne McGuire","dim1":0.2384,"dim2":-0.1093,"party":"Labour"},{"member":"Anne McIntosh","dim1":-0.183,"dim2":0.1521,"party":"Conservative"},{"member":"Anne McLaughlin","dim1":5.8436,"dim2":-6.5766,"party":"Scottish National Party"},{"member":"Anne Milton","dim1":-19.7501,"dim2":3.1111,"party":"Conservative"},{"member":"Anneliese Dodds","dim1":9.0931,"dim2":8.5981,"party":"Labour"},{"member":"Annette Brooke","dim1":-0.0418,"dim2":0.0599,"party":"Liberal Democrat"},{"member":"Anthony Baldry","dim1":-0.1896,"dim2":0.1561,"party":"Conservative"},{"member":"Anthony Timpson","dim1":-0.1709,"dim2":0.1325,"party":"Conservative"},{"member":"Antoinette Sandbach","dim1":-18.428,"dim2":2.993,"party":"Conservative"},{"member":"Arthur Soames","dim1":-0.1998,"dim2":0.1758,"party":"Conservative"},{"member":"Austin Mitchell","dim1":0.1951,"dim2":-0.0761,"party":"Labour"},{"member":"Bambos Charalambous","dim1":9.4194,"dim2":9.3214,"party":"Labour"},{"member":"Barbara Keeley","dim1":12.8423,"dim2":2.2221,"party":"Labour"},{"member":"Barry Gardiner","dim1":15.7455,"dim2":3.4282,"party":"Labour"},{"member":"Barry Sheerman","dim1":0.1996,"dim2":-0.09,"party":"Labour"},{"member":"Ben Bradley","dim1":-10.4671,"dim2":-8.0835,"party":"Conservative"},{"member":"Ben Gummer","dim1":-9.3167,"dim2":10.1591,"party":"Conservative"},{"member":"Ben Howlett","dim1":-8.9899,"dim2":9.8599,"party":"Conservative"},{"member":"Ben Lake","dim1":9.5572,"dim2":7.9907,"party":"Plaid Cymru"},{"member":"Benedict Gummer","dim1":-0.1507,"dim2":0.1369,"party":"Conservative"},{"member":"Benjamin Bradshaw","dim1":0.1954,"dim2":-0.0754,"party":"Labour"},{"member":"Bernard Jenkin","dim1":-0.2219,"dim2":0.1713,"party":"Conservative"},{"member":"Bill  Esterson","dim1":0.2384,"dim2":-0.1093,"party":"Labour"},{"member":"Bill Esterson","dim1":15.5212,"dim2":3.6201,"party":"Labour"},{"member":"Bill Grant","dim1":-10.5283,"dim2":-8.087,"party":"Conservative"},{"member":"Bill Wiggin","dim1":-19.2931,"dim2":2.8398,"party":"Conservative"},{"member":"Bim Afolami","dim1":-10.4413,"dim2":-8.0954,"party":"Conservative"},{"member":"Bob Blackman","dim1":-19.962,"dim2":2.1602,"party":"Conservative"},{"member":"Bob Stewart","dim1":-18.044,"dim2":0.9754,"party":"Conservative"},{"member":"Boris Johnson","dim1":-15.6423,"dim2":0.4639,"party":"Conservative"},{"member":"Brandon Lewis","dim1":-19.3197,"dim2":2.7199,"party":"Conservative"},{"member":"Brendan O'Hara","dim1":14.8462,"dim2":0.4538,"party":"Scottish National Party"},{"member":"Brian Binley","dim1":-0.2139,"dim2":0.1559,"party":"Conservative"},{"member":"Brian Donohoe","dim1":0.2384,"dim2":-0.1093,"party":"Labour"},{"member":"Bridget Phillipson","dim1":13.9847,"dim2":4.936,"party":"Labour"},{"member":"Brooks Newmark","dim1":-0.1896,"dim2":0.1561,"party":"Conservative"},{"member":"Byron Davies","dim1":-8.5664,"dim2":9.4532,"party":"Conservative"},{"member":"Callum McCaig","dim1":6.9496,"dim2":-7.5502,"party":"Scottish National Party"},{"member":"Calum Kerr","dim1":6.1994,"dim2":-6.9198,"party":"Scottish National Party"},{"member":"Carol Monaghan","dim1":14.7581,"dim2":0.7282,"party":"Scottish National Party"},{"member":"Caroline  Nokes","dim1":-0.978,"dim2":-0.9107,"party":"Conservative"},{"member":"Caroline Ansell","dim1":-9.1297,"dim2":9.9079,"party":"Conservative"},{"member":"Caroline Dinenage","dim1":-19.6597,"dim2":1.9413,"party":"Conservative"},{"member":"Caroline Flint","dim1":15.3379,"dim2":2.1929,"party":"Labour"},{"member":"Caroline Lucas","dim1":18.2774,"dim2":-0.1269,"party":"Green Party"},{"member":"Caroline Nokes","dim1":-19.5071,"dim2":3.4656,"party":"Conservative"},{"member":"Caroline Spelman","dim1":-0.1998,"dim2":0.1758,"party":"Conservative"},{"member":"Carolyn Harris","dim1":16.9361,"dim2":3.132,"party":"Labour"},{"member":"Cat Smith","dim1":15.8856,"dim2":1.5838,"party":"Labour"},{"member":"Catharine Hoey","dim1":0.2384,"dim2":-0.1093,"party":"Labour"},{"member":"Catherine McKinnell","dim1":15.2871,"dim2":3.0477,"party":"Labour"},{"member":"Catherine West","dim1":17.2607,"dim2":1.3185,"party":"Labour"},{"member":"Cathy Jamieson","dim1":0.2384,"dim2":-0.1093,"party":"Labour"},{"member":"Charles Cox","dim1":-0.1918,"dim2":0.1604,"party":"Conservative"},{"member":"Charles Hendry","dim1":-0.2306,"dim2":0.1796,"party":"Conservative"},{"member":"Charles Kennedy","dim1":-0.0322,"dim2":0.0821,"party":"Liberal Democrat"},{"member":"Charles Walker","dim1":-0.1998,"dim2":0.1758,"party":"Conservative"},{"member":"Charlie Elphicke","dim1":-18.7293,"dim2":4.381,"party":"Independent"},{"member":"Charlotte Leslie","dim1":-8.7113,"dim2":9.3456,"party":"Conservative"},{"member":"Cheryl Gillan","dim1":-0.2219,"dim2":0.1713,"party":"Conservative"},{"member":"Chi Onwurah","dim1":16.3229,"dim2":2.2545,"party":"Labour"},{"member":"Chinyelu Onwurah","dim1":0.2384,"dim2":-0.1093,"party":"Labour"},{"member":"Chloe Smith","dim1":-16.3402,"dim2":-1.1011,"party":"Conservative"},{"member":"Chloe Smith ; John Carswell","dim1":0.0912,"dim2":-0.0578,"party":"Conservative ; UK Independence Party"},{"member":"Chris Bryant","dim1":15.9933,"dim2":3.0067,"party":"Labour"},{"member":"Chris Davies","dim1":-19.1429,"dim2":1.36,"party":"Conservative"},{"member":"Chris Elmore","dim1":14.4142,"dim2":4.6378,"party":"Labour"},{"member":"Chris Evans","dim1":16.4887,"dim2":3.6457,"party":"Labour"},{"member":"Chris Grayling","dim1":-18.7466,"dim2":1.3637,"party":"Conservative"},{"member":"Chris Green","dim1":-20.4031,"dim2":2.6785,"party":"Conservative"},{"member":"Chris Heaton-Harris","dim1":-18.2414,"dim2":0.7073,"party":"Conservative"},{"member":"Chris Kelly","dim1":-0.1998,"dim2":0.1758,"party":"Conservative"},{"member":"Chris Law","dim1":14.4499,"dim2":0.5854,"party":"Scottish National Party"},{"member":"Chris Leslie","dim1":6.099,"dim2":-5.2909,"party":"Labour"},{"member":"Chris Philp","dim1":-20.2249,"dim2":2.7113,"party":"Conservative"},{"member":"Chris Pincher","dim1":-0.2139,"dim2":0.1559,"party":"Conservative"},{"member":"Chris Ruane","dim1":8.9586,"dim2":8.7793,"party":"Labour"},{"member":"Chris Skidmore","dim1":-20.1006,"dim2":2.3493,"party":"Conservative"},{"member":"Chris Stephens","dim1":16.34,"dim2":-0.4903,"party":"Scottish National Party"},{"member":"Chris White","dim1":-9.4929,"dim2":10.3322,"party":"Conservative"},{"member":"Chris Williamson","dim1":9.0112,"dim2":8.5065,"party":"Labour"},{"member":"Christian Matheson","dim1":16.9367,"dim2":2.5899,"party":"Labour"},{"member":"Christina Rees","dim1":15.5517,"dim2":2.2746,"party":"Labour"},{"member":"Christine Jardine","dim1":8.9255,"dim2":8.3593,"party":"Liberal Democrat"},{"member":"Christopher Bryant","dim1":0.2384,"dim2":-0.1093,"party":"Labour"},{"member":"Christopher Chope","dim1":-0.1199,"dim2":0.1331,"party":"Conservative"},{"member":"Christopher Farrelly","dim1":0.2384,"dim2":-0.1093,"party":"Labour"},{"member":"Christopher Grayling","dim1":-0.2219,"dim2":0.1713,"party":"Conservative"},{"member":"Christopher Leslie","dim1":0.1954,"dim2":-0.0754,"party":"Labour"},{"member":"Christopher Pincher","dim1":-19.1972,"dim2":1.702,"party":"Conservative"},{"member":"Christopher Ruane","dim1":0.2384,"dim2":-0.1093,"party":"Labour"},{"member":"Chuka Umunna","dim1":9.2086,"dim2":8.5895,"party":"Labour"},{"member":"Claire Perry","dim1":-19.5411,"dim2":2.5313,"party":"Conservative"},{"member":"Clive Betts","dim1":0.2384,"dim2":-0.1093,"party":"Labour"},{"member":"Clive Efford","dim1":16.8193,"dim2":2.7885,"party":"Labour"},{"member":"Clive Lewis","dim1":14.7092,"dim2":3.3322,"party":"Labour"},{"member":"Colin Clark","dim1":-10.5339,"dim2":-8.1269,"party":"Conservative"},{"member":"Colleen Fletcher","dim1":14.8529,"dim2":1.2051,"party":"Labour"},{"member":"Conor Burns","dim1":-20.4116,"dim2":2.5836,"party":"Conservative"},{"member":"Conor McGinn","dim1":14.3522,"dim2":2.9338,"party":"Labour"},{"member":"Conor Murphy","dim1":0.109,"dim2":-0.0101,"party":"Sinn Féin"},{"member":"Corri Wilson","dim1":5.2971,"dim2":-5.8577,"party":"Scottish National Party"},{"member":"Craig Mackinlay","dim1":-20.2245,"dim2":2.4775,"party":"Conservative"},{"member":"Craig Tracey","dim1":-20.1732,"dim2":2.2452,"party":"Conservative"},{"member":"Craig Whittaker","dim1":-18.3792,"dim2":4.5312,"party":"Conservative"},{"member":"Craig Williams","dim1":-9.2052,"dim2":10.1245,"party":"Conservative"},{"member":"Crispin Blunt","dim1":-18.3344,"dim2":0.9308,"party":"Conservative"},{"member":"Dame  Margaret Hodge","dim1":1.2972,"dim2":-1.1787,"party":"Labour"},{"member":"Dame  Rosie Winterton","dim1":6.7557,"dim2":-5.432,"party":"Labour"},{"member":"Dame Angela Watkinson","dim1":-4.351,"dim2":4.7625,"party":"Conservative"},{"member":"Dame Caroline Spelman","dim1":-15.5906,"dim2":-2.4246,"party":"Conservative"},{"member":"Dame Cheryl Gillan","dim1":-5.409,"dim2":-4.1696,"party":"Conservative"},{"member":"Dame Louise Ellman","dim1":2.1968,"dim2":2.5943,"party":"Labour"},{"member":"Dame Margaret Hodge","dim1":8.6878,"dim2":5.8294,"party":"Labour"},{"member":"Dame Rosie Winterton","dim1":0.0855,"dim2":0.0404,"party":"Labour"},{"member":"Damian Collins","dim1":-18.4285,"dim2":3.3305,"party":"Conservative"},{"member":"Damian Green","dim1":-19.8131,"dim2":2.824,"party":"Conservative"},{"member":"Damian Hinds","dim1":-14.2161,"dim2":7.0309,"party":"Conservative"},{"member":"Damien Moore","dim1":-10.5388,"dim2":-8.1099,"party":"Conservative"},{"member":"Dan Carden","dim1":9.4431,"dim2":9.2853,"party":"Labour"},{"member":"Dan Jarvis","dim1":15.7028,"dim2":2.7231,"party":"Labour"},{"member":"Daniel  Poulter","dim1":-0.1263,"dim2":0.1049,"party":"Conservative"},{"member":"Daniel Alexander","dim1":-0.1157,"dim2":0.129,"party":"Liberal Democrat"},{"member":"Daniel Byles","dim1":-0.2117,"dim2":0.1517,"party":"Conservative"},{"member":"Daniel Kawczynski","dim1":-19.1684,"dim2":1.5898,"party":"Conservative"},{"member":"Daniel Rogerson","dim1":-0.0156,"dim2":0.0603,"party":"Liberal Democrat"},{"member":"Daniel Zeichner","dim1":18.2193,"dim2":1.4744,"party":"Labour"},{"member":"Danielle Rowley","dim1":9.2973,"dim2":9.1385,"party":"Labour"},{"member":"Danny Kinahan","dim1":-2.0287,"dim2":2.9617,"party":"Ulster Unionist Party"},{"member":"Darren Jones","dim1":8.8991,"dim2":8.6368,"party":"Labour"},{"member":"David Amess","dim1":-0.2219,"dim2":0.1713,"party":"Conservative"},{"member":"David Anderson","dim1":0.2528,"dim2":-0.1751,"party":"Labour"},{"member":"David Blunkett","dim1":0.2384,"dim2":-0.1093,"party":"Labour"},{"member":"David Burrowes","dim1":-0.1568,"dim2":0.1525,"party":"Conservative"},{"member":"David Cameron","dim1":0.0393,"dim2":0.013,"party":"Conservative"},{"member":"David Clark","dim1":-0.2528,"dim2":0.1751,"party":"Conservative"},{"member":"David Crausby","dim1":0.2384,"dim2":-0.1093,"party":"Labour"},{"member":"David Davies","dim1":-0.2528,"dim2":0.1751,"party":"Conservative"},{"member":"David Davis","dim1":-0.183,"dim2":0.1521,"party":"Conservative"},{"member":"David Duguid","dim1":-10.5681,"dim2":-8.1123,"party":"Conservative"},{"member":"David Evennett","dim1":-16.9802,"dim2":4.2324,"party":"Conservative"},{"member":"David Francis","dim1":0.2384,"dim2":-0.1093,"party":"Labour"},{"member":"David Gauke","dim1":-0.2528,"dim2":0.1751,"party":"Conservative"},{"member":"David Hamilton","dim1":0.223,"dim2":-0.1074,"party":"Labour"},{"member":"David Hanson","dim1":5.2915,"dim2":4.9942,"party":"Labour"},{"member":"David Havard","dim1":0.2384,"dim2":-0.1093,"party":"Labour"},{"member":"David Heath","dim1":-0.183,"dim2":0.1521,"party":"Liberal Democrat"},{"member":"David Heyes","dim1":0.109,"dim2":-0.0101,"party":"Labour"},{"member":"David Jones","dim1":-0.2528,"dim2":0.1751,"party":"Conservative"},{"member":"David Lammy","dim1":0.2384,"dim2":-0.1093,"party":"Labour"},{"member":"David Laws","dim1":-0.071,"dim2":0.1013,"party":"Liberal Democrat"},{"member":"David Lidington","dim1":-0.1378,"dim2":0.1245,"party":"Conservative"},{"member":"David Linden","dim1":7.8424,"dim2":6.9716,"party":"Scottish National Party"},{"member":"David Mackintosh","dim1":-8.9249,"dim2":9.7931,"party":"Conservative"},{"member":"David Morris","dim1":-19.8666,"dim2":3.0625,"party":"Conservative"},{"member":"David Mowat","dim1":-9.7629,"dim2":10.7134,"party":"Conservative"},{"member":"David Mundell","dim1":-17.541,"dim2":0.3531,"party":"Conservative"},{"member":"David Nuttall","dim1":-0.1789,"dim2":0.148,"party":"Conservative"},{"member":"David Ruffley","dim1":-0.1378,"dim2":0.1245,"party":"Conservative"},{"member":"David Rutley","dim1":-19.6848,"dim2":3.3317,"party":"Conservative"},{"member":"David Simpson","dim1":-13.5338,"dim2":-2.3778,"party":"Democratic Unionist Party"},{"member":"David T. C. Davies","dim1":-18.6831,"dim2":1.625,"party":"Conservative"},{"member":"David Tredinnick","dim1":-19.1446,"dim2":2.3418,"party":"Conservative"},{"member":"David Warburton","dim1":-19.3237,"dim2":1.9479,"party":"Conservative"},{"member":"David Ward","dim1":0.0272,"dim2":0.0325,"party":"Liberal Democrat"},{"member":"David Watts","dim1":0.109,"dim2":-0.0101,"party":"Labour"},{"member":"David Willetts","dim1":-0.2098,"dim2":0.1518,"party":"Conservative"},{"member":"David Winnick","dim1":0.2384,"dim2":-0.1093,"party":"Labour"},{"member":"David Wright","dim1":0.2384,"dim2":-0.1093,"party":"Labour"},{"member":"Dawn Butler","dim1":15.8063,"dim2":1.7311,"party":"Labour"},{"member":"Dawn Primarolo","dim1":0.109,"dim2":-0.0101,"party":"Second Deputy Chairman of Ways and Means"},{"member":"Debbie Abrahams","dim1":14.9735,"dim2":0.3875,"party":"Labour"},{"member":"Deidre Brock","dim1":15.2657,"dim2":0.3448,"party":"Scottish National Party"},{"member":"Dennis Skinner","dim1":0.2528,"dim2":-0.1751,"party":"Labour"},{"member":"Derek Thomas","dim1":-19.7249,"dim2":2.3109,"party":"Conservative"},{"member":"Derek Twigg","dim1":13.0945,"dim2":1.2328,"party":"Labour"},{"member":"Desmond Swayne","dim1":-0.1896,"dim2":0.1561,"party":"Conservative"},{"member":"Diana Johnson","dim1":14.6479,"dim2":3.7014,"party":"Labour"},{"member":"Diane Abbott","dim1":0.2384,"dim2":-0.1093,"party":"Labour"},{"member":"Dominic Grieve","dim1":-0.1896,"dim2":0.1561,"party":"Conservative"},{"member":"Dominic Raab","dim1":-19.6072,"dim2":1.8497,"party":"Conservative"},{"member":"Donald Foster","dim1":-0.2528,"dim2":0.1751,"party":"Liberal Democrat"},{"member":"Douglas Alexander","dim1":0.2384,"dim2":-0.1093,"party":"Labour"},{"member":"Douglas Chapman","dim1":14.2302,"dim2":0.0884,"party":"Scottish National Party"},{"member":"Douglas Ross","dim1":-10.4486,"dim2":-7.9091,"party":"Conservative"},{"member":"Dr Alan Whitehead","dim1":17.529,"dim2":1.7404,"party":"Labour"},{"member":"Dr Alasdair McDonnell","dim1":4.8283,"dim2":-4.999,"party":"Social Democratic & Labour Party"},{"member":"Dr Andrew Murrison","dim1":-18.9711,"dim2":2.2843,"party":"Conservative"},{"member":"Dr Caroline Johnson","dim1":-14.092,"dim2":-4.3603,"party":"Conservative"},{"member":"Dr Dan Poulter","dim1":-10.7532,"dim2":-0.044,"party":"Conservative"},{"member":"Dr David Drew","dim1":8.7737,"dim2":8.6144,"party":"Labour"},{"member":"Dr Eilidh Whiteford","dim1":6.9585,"dim2":-7.5959,"party":"Scottish National Party"},{"member":"Dr James Davies","dim1":-8.2265,"dim2":8.7942,"party":"Conservative"},{"member":"Dr Julian Lewis","dim1":-18.3837,"dim2":0.6992,"party":"Conservative"},{"member":"Dr Liam Fox","dim1":-16.0631,"dim2":0.8461,"party":"Conservative"},{"member":"Dr Lisa Cameron","dim1":14.9989,"dim2":0.7606,"party":"Scottish National Party"},{"member":"Dr Matthew Offord","dim1":-19.6573,"dim2":2.2164,"party":"Conservative"},{"member":"Dr Paul Monaghan","dim1":6.069,"dim2":-6.6284,"party":"Scottish National Party"},{"member":"Dr Paul Williams","dim1":9.334,"dim2":8.273,"party":"Labour"},{"member":"Dr Philippa Whitford","dim1":14.8936,"dim2":-0.2037,"party":"Scottish National Party"},{"member":"Dr Phillip Lee","dim1":-19.5614,"dim2":3.2371,"party":"Conservative"},{"member":"Dr Poulter","dim1":-4.5083,"dim2":5.277,"party":"Conservative"},{"member":"Dr Roberta Blackman-Woods","dim1":13.0987,"dim2":2.1264,"party":"Labour"},{"member":"Dr Rosena Allin-Khan","dim1":13.0556,"dim2":3.6714,"party":"Labour"},{"member":"Dr Rupa Huq","dim1":16.9337,"dim2":2.3774,"party":"Labour"},{"member":"Dr Sarah Wollaston","dim1":-17.961,"dim2":2.6897,"party":"Conservative"},{"member":"Dr Tania Mathias","dim1":-8.8821,"dim2":9.9235,"party":"Conservative"},{"member":"Dr Thérèse Coffey","dim1":-19.3004,"dim2":3.1951,"party":"Conservative"},{"member":"Drew Hendry","dim1":15.8029,"dim2":-0.2305,"party":"Scottish National Party"},{"member":"Duncan Hames","dim1":-0.0418,"dim2":0.0599,"party":"Liberal Democrat"},{"member":"Eddie Hughes","dim1":-10.2987,"dim2":-7.8989,"party":"Conservative"},{"member":"Edward Argar","dim1":-20.5195,"dim2":2.7004,"party":"Conservative"},{"member":"Edward Balls","dim1":0.2384,"dim2":-0.1093,"party":"Labour"},{"member":"Edward Davey","dim1":-0.1651,"dim2":0.1241,"party":"Liberal Democrat"},{"member":"Edward Garnier","dim1":-0.1609,"dim2":0.1565,"party":"Conservative"},{"member":"Edward Leigh","dim1":-0.1587,"dim2":0.1523,"party":"Conservative"},{"member":"Edward Miliband","dim1":14.2554,"dim2":3.7357,"party":"Labour"},{"member":"Edward Timpson","dim1":-9.2067,"dim2":9.8461,"party":"Conservative"},{"member":"Edward Vaizey","dim1":-0.1299,"dim2":0.1091,"party":"Conservative"},{"member":"Eilidh Whiteford","dim1":0.2384,"dim2":-0.1093,"party":"Scottish National"},{"member":"Eleanor Laing","dim1":0.109,"dim2":-0.0101,"party":"Conservative"},{"member":"Eleanor Smith","dim1":9.2551,"dim2":9.0819,"party":"Labour"},{"member":"Elfyn Llwyd","dim1":0.1951,"dim2":-0.0761,"party":"Plaid Cymru"},{"member":"Elizabeth Kendall","dim1":0.2384,"dim2":-0.1093,"party":"Labour"},{"member":"Elizabeth Truss","dim1":-17.8548,"dim2":0.5281,"party":"Conservative"},{"member":"Ellie Reeves","dim1":8.9131,"dim2":8.7438,"party":"Labour"},{"member":"Emily Thornberry","dim1":15.6478,"dim2":3.0216,"party":"Labour"},{"member":"Emma Dent Coad","dim1":8.9033,"dim2":8.6716,"party":"Labour"},{"member":"Emma Hardy","dim1":9.0003,"dim2":8.8671,"party":"Labour"},{"member":"Emma Lewell-Buck","dim1":0.2384,"dim2":-0.1093,"party":"Labour"},{"member":"Emma Little Pengelly","dim1":-9.6197,"dim2":-7.5487,"party":"Democratic Unionist Party"},{"member":"Emma Reynolds","dim1":9.1072,"dim2":0.0154,"party":"Labour"},{"member":"Eric Joyce","dim1":0.109,"dim2":-0.0101,"party":"Independent"},{"member":"Eric Ollerenshaw","dim1":-0.2306,"dim2":0.1796,"party":"Conservative"},{"member":"Eric Pickles","dim1":-0.2306,"dim2":0.1796,"party":"Conservative"},{"member":"Esther McVey","dim1":-10.6163,"dim2":-7.9187,"party":"Conservative"},{"member":"Fabian Hamilton","dim1":14.6969,"dim2":3.5384,"party":"Labour"},{"member":"Faisal Rashid","dim1":8.8839,"dim2":8.702,"party":"Labour"},{"member":"Fiona Bruce","dim1":-19.498,"dim2":1.6933,"party":"Conservative"},{"member":"Fiona Mactaggart","dim1":7.5766,"dim2":-6.5302,"party":"Labour"},{"member":"Fiona O'Donnell","dim1":0.2384,"dim2":-0.1093,"party":"Labour"},{"member":"Fiona Onasanya","dim1":9.1008,"dim2":8.9033,"party":"Labour"},{"member":"Francie Molloy","dim1":0.109,"dim2":-0.0101,"party":"Sinn Féin"},{"member":"Francis Maude","dim1":-0.1709,"dim2":0.1325,"party":"Conservative"},{"member":"Frank Dobson","dim1":0.109,"dim2":-0.0101,"party":"Labour"},{"member":"Frank Doran","dim1":0.2384,"dim2":-0.1093,"party":"Labour"},{"member":"Frank Field","dim1":6.2445,"dim2":-1.1357,"party":"Labour"},{"member":"Frank Roy","dim1":0.2384,"dim2":-0.1093,"party":"Labour"},{"member":"Gareth Johnson","dim1":-20.0909,"dim2":2.114,"party":"Conservative"},{"member":"Gareth Snell","dim1":9.5311,"dim2":8.0585,"party":"Labour"},{"member":"Gareth Thomas","dim1":14.5793,"dim2":4.3873,"party":"Labour"},{"member":"Gary Streeter","dim1":-0.1998,"dim2":0.1758,"party":"Conservative"},{"member":"Gavin Barwell","dim1":-9.3041,"dim2":10.0657,"party":"Conservative"},{"member":"Gavin Newlands","dim1":15.765,"dim2":-0.4091,"party":"Scottish National Party"},{"member":"Gavin Robinson","dim1":-14.0171,"dim2":-2.6058,"party":"Democratic Unionist Party"},{"member":"Gavin Shuker","dim1":0.2384,"dim2":-0.1093,"party":"Labour"},{"member":"Gavin Williamson","dim1":-19.9262,"dim2":2.7047,"party":"Conservative"},{"member":"Ged Killen","dim1":7.1665,"dim2":7.0828,"party":"Labour"},{"member":"Gemma Doyle","dim1":0.2384,"dim2":-0.1093,"party":"Labour"},{"member":"Geoffrey Clifton-Brown","dim1":-13.3722,"dim2":6.9285,"party":"Conservative"},{"member":"Geoffrey Robinson","dim1":0.1953,"dim2":-0.0772,"party":"Labour"},{"member":"George Duncan Smith","dim1":-0.2528,"dim2":0.1751,"party":"Conservative"},{"member":"George Eustice","dim1":-19.2758,"dim2":1.7688,"party":"Conservative"},{"member":"George Freeman","dim1":-18.5705,"dim2":2.475,"party":"Conservative"},{"member":"George Galloway","dim1":0.1051,"dim2":-0.0452,"party":"Respect"},{"member":"George Hollingbery","dim1":-18.6257,"dim2":0.4971,"party":"Conservative"},{"member":"George Howarth","dim1":0.2384,"dim2":-0.1093,"party":"Labour"},{"member":"George Kerevan","dim1":6.9512,"dim2":-7.6826,"party":"Scottish National Party"},{"member":"George Mudie","dim1":0.2097,"dim2":-0.1431,"party":"Labour"},{"member":"George Osborne","dim1":-0.071,"dim2":0.1013,"party":"Conservative"},{"member":"George Young","dim1":-0.2528,"dim2":0.1751,"party":"Conservative"},{"member":"Geraint Davies","dim1":14.6979,"dim2":2.2388,"party":"Labour"},{"member":"Gerald Jones","dim1":17.0837,"dim2":2.9106,"party":"Labour"},{"member":"Gerald Kaufman","dim1":0.2384,"dim2":-0.1093,"party":"Labour"},{"member":"Gerard Killen","dim1":1.8645,"dim2":1.7201,"party":"Labour"},{"member":"Gerard Sutcliffe","dim1":0.1953,"dim2":-0.0772,"party":"Labour"},{"member":"Giles Watling","dim1":-10.1782,"dim2":-7.9061,"party":"Conservative"},{"member":"Gill Furniss","dim1":14.7084,"dim2":4.5495,"party":"Labour"},{"member":"Gillian Keegan","dim1":-10.4983,"dim2":-8.0595,"party":"Conservative"},{"member":"Gisela Stuart","dim1":0.2384,"dim2":-0.1093,"party":"Labour"},{"member":"Glenda Jackson","dim1":0.2384,"dim2":-0.1093,"party":"Labour"},{"member":"Gloria De Piero","dim1":15.4692,"dim2":3.4711,"party":"Labour"},{"member":"Glyn Davies","dim1":-20.0879,"dim2":2.2414,"party":"Conservative"},{"member":"Gordon Banks","dim1":0.2384,"dim2":-0.1093,"party":"Labour"},{"member":"Gordon Birtwistle","dim1":0.0291,"dim2":0.0326,"party":"Liberal Democrat"},{"member":"Gordon Henderson","dim1":-20.4912,"dim2":2.8731,"party":"Conservative"},{"member":"Gordon Marsden","dim1":17.4975,"dim2":2.3515,"party":"Labour"},{"member":"Graeme Morrice","dim1":0.2384,"dim2":-0.1093,"party":"Labour"},{"member":"Graham  Jones","dim1":0.1964,"dim2":-0.0859,"party":"Labour"},{"member":"Graham Allen","dim1":0.2384,"dim2":-0.1093,"party":"Labour"},{"member":"Graham Brady","dim1":-0.1998,"dim2":0.1758,"party":"Conservative"},{"member":"Graham Evans","dim1":-10.0316,"dim2":10.9473,"party":"Conservative"},{"member":"Graham Jones","dim1":6.1377,"dim2":-5.0452,"party":"Labour"},{"member":"Graham P Jones","dim1":7.6313,"dim2":7.4186,"party":"Labour"},{"member":"Graham Stringer","dim1":5.3645,"dim2":-2.8671,"party":"Labour"},{"member":"Graham Stuart","dim1":-17.9057,"dim2":0.8309,"party":"Conservative"},{"member":"Grahame Morris","dim1":13.5886,"dim2":5.6519,"party":"Labour"},{"member":"Grant Shapps","dim1":-20.0397,"dim2":2.555,"party":"Conservative"},{"member":"Greg Clark","dim1":-18.4774,"dim2":1.0253,"party":"Conservative"},{"member":"Greg Hands","dim1":-19.4874,"dim2":1.8834,"party":"Conservative"},{"member":"Greg Mulholland","dim1":7.2818,"dim2":-6.9222,"party":"Liberal Democrat"},{"member":"Gregg McClymont","dim1":0.2384,"dim2":-0.1093,"party":"Labour"},{"member":"Gregory Barker","dim1":-0.2528,"dim2":0.1751,"party":"Conservative"},{"member":"Gregory Campbell","dim1":-0.0674,"dim2":0.0931,"party":"Democratic Unionist"},{"member":"Gregory Hands","dim1":-0.2528,"dim2":0.1751,"party":"Conservative"},{"member":"Gregory Knight","dim1":-0.1896,"dim2":0.1561,"party":"Conservative"},{"member":"Gregory Mulholland","dim1":-0.0197,"dim2":0.0644,"party":"Liberal Democrat"},{"member":"Guto Bebb","dim1":-19.2086,"dim2":2.2317,"party":"Conservative"},{"member":"Guy Opperman","dim1":-19.207,"dim2":1.6626,"party":"Conservative"},{"member":"Hannah Bardell","dim1":13.4738,"dim2":0.0892,"party":"Scottish National Party"},{"member":"Harriet Harman","dim1":0.109,"dim2":-0.0101,"party":"Labour"},{"member":"Harriett Baldwin","dim1":-20.1513,"dim2":2.467,"party":"Conservative"},{"member":"Hazel Blears","dim1":0.109,"dim2":-0.0101,"party":"Labour"},{"member":"Heather Wheeler","dim1":-8.1229,"dim2":8.7195,"party":"Conservative"},{"member":"Heidi Alexander","dim1":13.7799,"dim2":-1.083,"party":"Labour"},{"member":"Heidi Allen","dim1":-18.3093,"dim2":3.0391,"party":"Conservative"},{"member":"Helen Goodman","dim1":16.4733,"dim2":2.2878,"party":"Labour"},{"member":"Helen Grant","dim1":-0.2528,"dim2":0.1751,"party":"Conservative"},{"member":"Helen Hayes","dim1":17.9215,"dim2":1.7485,"party":"Labour"},{"member":"Helen Jones","dim1":14.1158,"dim2":2.6668,"party":"Labour"},{"member":"Helen Whately","dim1":-20.1742,"dim2":2.6491,"party":"Conservative"},{"member":"Henry Bellingham","dim1":-0.2306,"dim2":0.1796,"party":"Conservative"},{"member":"Henry Smith","dim1":-19.4469,"dim2":2.7264,"party":"Conservative"},{"member":"Hilary Benn","dim1":17.2704,"dim2":2.6759,"party":"Labour"},{"member":"Holly Lynch","dim1":16.2485,"dim2":3.4407,"party":"Labour"},{"member":"Hugh Bayley","dim1":0.2384,"dim2":-0.1093,"party":"Labour"},{"member":"Hugh Gaffney","dim1":9.1732,"dim2":9.0976,"party":"Labour"},{"member":"Hugh Robertson","dim1":-0.2139,"dim2":0.1559,"party":"Conservative"},{"member":"Hugo Swire","dim1":-0.2528,"dim2":0.1751,"party":"Conservative"},{"member":"Huw Irranca-Davies","dim1":0.1486,"dim2":-0.1405,"party":"Labour"},{"member":"Huw Merriman","dim1":-19.5812,"dim2":2.5092,"party":"Conservative"},{"member":"Hywel Williams","dim1":16.4816,"dim2":-0.7122,"party":"Plaid Cymru"},{"member":"Iain McKenzie","dim1":0.2384,"dim2":-0.1093,"party":"Labour"},{"member":"Iain Stewart","dim1":-20.3606,"dim2":2.5938,"party":"Conservative"},{"member":"Iain Wright","dim1":0.2384,"dim2":-0.1093,"party":"Labour"},{"member":"Ian Austin","dim1":12.4769,"dim2":4.0335,"party":"Labour"},{"member":"Ian Blackford","dim1":15.179,"dim2":-0.0486,"party":"Scottish National Party"},{"member":"Ian C. Lucas","dim1":14.6933,"dim2":2.4748,"party":"Labour"},{"member":"Ian Davidson","dim1":0.2384,"dim2":-0.1093,"party":"Labour"},{"member":"Ian Lavery","dim1":16.6567,"dim2":1.5675,"party":"Labour"},{"member":"Ian Liddell-Grainger","dim1":-0.1998,"dim2":0.1758,"party":"Conservative"},{"member":"Ian Lucas","dim1":0.2384,"dim2":-0.1093,"party":"Labour"},{"member":"Ian Mearns","dim1":16.8934,"dim2":2.8317,"party":"Labour"},{"member":"Ian Murray","dim1":16.2593,"dim2":2.3313,"party":"Labour"},{"member":"Ian Paisley","dim1":-12.5168,"dim2":-3.2976,"party":"Democratic Unionist Party"},{"member":"Ian Paisley Junior","dim1":0.109,"dim2":-0.0101,"party":"Democratic Unionist"},{"member":"Ian Swales","dim1":-0.2219,"dim2":0.1713,"party":"Liberal Democrat"},{"member":"Ifor Irranca-Davies","dim1":0.2384,"dim2":-0.1093,"party":"Labour"},{"member":"Imran Hussain","dim1":15.9248,"dim2":3.1168,"party":"Labour"},{"member":"Ivan Lewis","dim1":0.1521,"dim2":-0.0422,"party":"Labour"},{"member":"Jack Brereton","dim1":-9.969,"dim2":-7.6261,"party":"Conservative"},{"member":"Jack Dromey","dim1":14.0574,"dim2":3.7226,"party":"Labour"},{"member":"Jack Lopresti","dim1":-18.5768,"dim2":1.5574,"party":"Conservative"},{"member":"Jackie Doyle-Price","dim1":-18.8157,"dim2":0.4862,"party":"Conservative"},{"member":"Jacob Rees-Mogg","dim1":-0.1568,"dim2":0.1525,"party":"Conservative"},{"member":"Jake Berry","dim1":-19.6049,"dim2":1.7062,"party":"Conservative"},{"member":"James Arbuthnot","dim1":-0.2528,"dim2":0.1751,"party":"Conservative"},{"member":"James Berry","dim1":-9.0283,"dim2":9.6954,"party":"Conservative"},{"member":"James Brokenshire","dim1":-16.6966,"dim2":3.5789,"party":"Conservative"},{"member":"James Brown","dim1":0.109,"dim2":-0.0101,"party":"Labour"},{"member":"James Cartlidge","dim1":-20.5271,"dim2":2.8297,"party":"Conservative"},{"member":"James Cleverly","dim1":-20.0962,"dim2":2.404,"party":"Conservative"},{"member":"James Cunningham","dim1":0.2384,"dim2":-0.1093,"party":"Labour"},{"member":"James Dowd","dim1":0.2384,"dim2":-0.1093,"party":"Labour"},{"member":"James Duddridge","dim1":-19.1078,"dim2":0.9253,"party":"Conservative"},{"member":"James Fitzpatrick","dim1":0.2384,"dim2":-0.1093,"party":"Labour"},{"member":"James Frith","dim1":8.9892,"dim2":8.9009,"party":"Labour"},{"member":"James Gray","dim1":-16.0456,"dim2":1.2794,"party":"Conservative"},{"member":"James Heappey","dim1":-19.9099,"dim2":2.4662,"party":"Conservative"},{"member":"James Hood","dim1":0.109,"dim2":-0.0101,"party":"Labour"},{"member":"James Howarth","dim1":-0.1998,"dim2":0.1758,"party":"Conservative"},{"member":"James McGovern","dim1":0.2384,"dim2":-0.1093,"party":"Labour"},{"member":"James Morris","dim1":-20.5721,"dim2":2.7154,"party":"Conservative"},{"member":"James Murphy","dim1":0.1954,"dim2":-0.0754,"party":"Labour"},{"member":"James Paice","dim1":-0.1157,"dim2":0.129,"party":"Conservative"},{"member":"James Sheridan","dim1":0.2384,"dim2":-0.1093,"party":"Labour"},{"member":"James Wharton","dim1":-9.5822,"dim2":10.3475,"party":"Conservative"},{"member":"Jamie Stone","dim1":7.8342,"dim2":7.4413,"party":"Liberal Democrat"},{"member":"Jamieson Reed","dim1":0.2384,"dim2":-0.1093,"party":"Labour"},{"member":"Jane  Ellison","dim1":-0.2306,"dim2":0.1796,"party":"Conservative"},{"member":"Jane Ellison","dim1":-9.8293,"dim2":10.7783,"party":"Conservative"},{"member":"Janet Daby","dim1":1.1335,"dim2":1.5178,"party":"Labour"},{"member":"Jared O'Mara","dim1":4.291,"dim2":3.9916,"party":"Labour"},{"member":"Jason McCartney","dim1":-7.6923,"dim2":8.8589,"party":"Conservative"},{"member":"Jeff Smith","dim1":9.6013,"dim2":1.8089,"party":"Labour"},{"member":"Jeffrey Donaldson","dim1":0.0144,"dim2":0.0505,"party":"Democratic Unionist"},{"member":"Jennifer Willott","dim1":-0.1998,"dim2":0.1758,"party":"Liberal Democrat"},{"member":"Jenny Chapman","dim1":15.6318,"dim2":2.7293,"party":"Labour"},{"member":"Jeremy Browne","dim1":-0.1998,"dim2":0.1758,"party":"Liberal Democrat"},{"member":"Jeremy Corbyn","dim1":14.3739,"dim2":3.2622,"party":"Labour"},{"member":"Jeremy Hunt","dim1":-0.1077,"dim2":0.1135,"party":"Conservative"},{"member":"Jeremy Lefroy","dim1":-17.5736,"dim2":0.7955,"party":"Conservative"},{"member":"Jeremy Quin","dim1":-20.4143,"dim2":2.6884,"party":"Conservative"},{"member":"Jeremy Wright","dim1":-19.3946,"dim2":2.0327,"party":"Conservative"},{"member":"Jess Phillips","dim1":15.9067,"dim2":1.5409,"party":"Labour"},{"member":"Jesse Norman","dim1":-18.4971,"dim2":0.7031,"party":"Conservative"},{"member":"Jessica Lee","dim1":-0.0322,"dim2":0.0821,"party":"Conservative"},{"member":"Jessica Morden","dim1":16.0424,"dim2":3.67,"party":"Labour"},{"member":"Jim Dowd","dim1":7.1282,"dim2":-6.4801,"party":"Labour"},{"member":"Jim Fitzpatrick","dim1":16.111,"dim2":2.4582,"party":"Labour"},{"member":"Jim McMahon","dim1":15.68,"dim2":3.4988,"party":"Labour"},{"member":"Jim Shannon","dim1":-14.0461,"dim2":-2.8092,"party":"Democratic Unionist Party"},{"member":"Jo Churchill","dim1":-19.5123,"dim2":3.1564,"party":"Conservative"},{"member":"Jo Cox","dim1":1.8537,"dim2":-1.6684,"party":"Labour"},{"member":"Jo Platt","dim1":9.1655,"dim2":9.024,"party":"Labour"},{"member":"Jo Stevens","dim1":16.8109,"dim2":2.1485,"party":"Labour"},{"member":"Jo Swinson","dim1":6.2563,"dim2":5.7162,"party":"Liberal Democrat"},{"member":"Joan Ruddock","dim1":0.2384,"dim2":-0.1093,"party":"Labour"},{"member":"Joan Ryan","dim1":14.1524,"dim2":3.0814,"party":"Labour"},{"member":"Joan Walley","dim1":0.2384,"dim2":-0.1093,"party":"Labour"},{"member":"Joanna Cherry","dim1":15.1263,"dim2":0.4833,"party":"Scottish National Party"},{"member":"John Baron","dim1":-0.1157,"dim2":0.129,"party":"Conservative"},{"member":"John Bercow","dim1":0.109,"dim2":-0.0101,"party":"Speaker of the House of Commons"},{"member":"John Cable","dim1":-0.1163,"dim2":0.1289,"party":"Liberal Democrat"},{"member":"John Carswell","dim1":0.0179,"dim2":0.0477,"party":"UK Independence Party"},{"member":"John Cryer","dim1":15.4084,"dim2":1.9946,"party":"Labour"},{"member":"John Denham","dim1":0.2384,"dim2":-0.1093,"party":"Labour"},{"member":"John Durkan","dim1":0.2384,"dim2":-0.1093,"party":"Social Democratic & Labour Party"},{"member":"John Glen","dim1":-20.3455,"dim2":2.5977,"party":"Conservative"},{"member":"John Grogan","dim1":9.1967,"dim2":8.9632,"party":"Labour"},{"member":"John Hayes","dim1":-0.167,"dim2":0.124,"party":"Conservative"},{"member":"John Healey","dim1":16.6521,"dim2":3.0601,"party":"Labour"},{"member":"John Hemming","dim1":-0.1998,"dim2":0.1758,"party":"Liberal Democrat"},{"member":"John Howell","dim1":-18.6278,"dim2":1.9099,"party":"Conservative"},{"member":"John Lamont","dim1":-10.4573,"dim2":-7.9557,"party":"Conservative"},{"member":"John Lancaster","dim1":-0.2528,"dim2":0.1751,"party":"Conservative"},{"member":"John Leech","dim1":-0.0752,"dim2":0.1054,"party":"Liberal Democrat"},{"member":"John Mann","dim1":14.2955,"dim2":2.2682,"party":"Labour"},{"member":"John Mc Nally","dim1":5.4824,"dim2":-6.2226,"party":"Scottish National Party"},{"member":"John McDonnell","dim1":16.583,"dim2":2.6522,"party":"Labour"},{"member":"John McNally","dim1":8.3047,"dim2":6.83,"party":"Scottish National Party"},{"member":"John Nicolson","dim1":6.2161,"dim2":-6.7665,"party":"Scottish National Party"},{"member":"John Penrose","dim1":-20.4505,"dim2":2.5744,"party":"Conservative"},{"member":"John Pugh","dim1":7.2081,"dim2":-7.0311,"party":"Liberal Democrat"},{"member":"John Redwood","dim1":-20.1312,"dim2":2.0918,"party":"Conservative"},{"member":"John Robertson","dim1":0.2384,"dim2":-0.1093,"party":"Labour"},{"member":"John Spellar","dim1":15.5397,"dim2":3.3008,"party":"Labour"},{"member":"John Stanley","dim1":-0.2219,"dim2":0.1713,"party":"Conservative"},{"member":"John Stevenson","dim1":-18.9778,"dim2":1.3268,"party":"Conservative"},{"member":"John Straw","dim1":0.2384,"dim2":-0.1093,"party":"Labour"},{"member":"John Thurso","dim1":-0.2528,"dim2":0.1751,"party":"Liberal Democrat"},{"member":"John Twigg","dim1":0.2384,"dim2":-0.1093,"party":"Labour"},{"member":"John Whittingdale","dim1":-0.2117,"dim2":0.1517,"party":"Conservative"},{"member":"John Woodcock","dim1":12.049,"dim2":2.6824,"party":"Independent"},{"member":"Johnny Mercer","dim1":-18.448,"dim2":1.9501,"party":"Conservative"},{"member":"Jon Cruddas","dim1":16.0717,"dim2":3.2768,"party":"Labour"},{"member":"Jon Trickett","dim1":14.5926,"dim2":1.76,"party":"Labour"},{"member":"Jonathan  Edwards","dim1":0.2384,"dim2":-0.1093,"party":"Plaid Cymru"},{"member":"Jonathan Ashworth","dim1":16.1697,"dim2":3.6711,"party":"Labour"},{"member":"Jonathan Cruddas","dim1":0.2384,"dim2":-0.1093,"party":"Labour"},{"member":"Jonathan Djanogly","dim1":-0.2219,"dim2":0.1713,"party":"Conservative"},{"member":"Jonathan Edwards","dim1":17.2508,"dim2":-0.4159,"party":"Plaid Cymru"},{"member":"Jonathan Evans","dim1":-0.2528,"dim2":0.1751,"party":"Conservative"},{"member":"Jonathan Lord","dim1":0.109,"dim2":-0.0101,"party":"Conservative"},{"member":"Jonathan Reynolds","dim1":16.5304,"dim2":2.969,"party":"Labour"},{"member":"Joseph Benton","dim1":0.2384,"dim2":-0.1093,"party":"Labour"},{"member":"Joseph Johnson","dim1":-19.7497,"dim2":2.5295,"party":"Conservative"},{"member":"Joseph Meale","dim1":0.2384,"dim2":-0.1093,"party":"Labour"},{"member":"Judith Cummins","dim1":14.9101,"dim2":3.9141,"party":"Labour"},{"member":"Julia Dockerill","dim1":-0.647,"dim2":-0.48,"party":"Conservative"},{"member":"Julia Lopez","dim1":-9.4097,"dim2":-7.4303,"party":"Conservative"},{"member":"Julian Brazier","dim1":-0.2528,"dim2":0.1751,"party":"Conservative"},{"member":"Julian Huppert","dim1":-0.1998,"dim2":0.1758,"party":"Liberal Democrat"},{"member":"Julian Knight","dim1":-19.7934,"dim2":2.4466,"party":"Conservative"},{"member":"Julian Lewis","dim1":-0.1609,"dim2":0.1565,"party":"Conservative"},{"member":"Julian Smith","dim1":-20.1004,"dim2":2.6039,"party":"Conservative"},{"member":"Julian Sturdy","dim1":-20.5674,"dim2":2.8384,"party":"Conservative"},{"member":"Julie  Elliott","dim1":0.2384,"dim2":-0.1093,"party":"Labour"},{"member":"Julie  Hilling","dim1":0.2384,"dim2":-0.1093,"party":"Labour"},{"member":"Julie Cooper","dim1":15.2686,"dim2":3.6471,"party":"Labour"},{"member":"Julie Elliott","dim1":15.2413,"dim2":3.4428,"party":"Labour"},{"member":"Justin Madders","dim1":17.2723,"dim2":2.4584,"party":"Labour"},{"member":"Justin Tomlinson","dim1":-20.1315,"dim2":3.107,"party":"Conservative"},{"member":"Justine Greening","dim1":-18.5619,"dim2":0.7605,"party":"Conservative"},{"member":"Karen Bradley","dim1":-19.2596,"dim2":1.9133,"party":"Conservative"},{"member":"Karen Buck","dim1":0.2384,"dim2":-0.1093,"party":"Labour"},{"member":"Karen Lee","dim1":4.7978,"dim2":4.7485,"party":"Labour"},{"member":"Karen Lumley","dim1":-6.1204,"dim2":6.9952,"party":"Conservative"},{"member":"Karin Smyth","dim1":16.2575,"dim2":3.3333,"party":"Labour"},{"member":"Karl McCartney","dim1":-9.0819,"dim2":9.8102,"party":"Conservative"},{"member":"Karl Turner","dim1":14.1416,"dim2":2.6282,"party":"Labour"},{"member":"Kate  Green","dim1":0.2384,"dim2":-0.1093,"party":"Labour"},{"member":"Kate Green","dim1":16.7401,"dim2":2.4627,"party":"Labour"},{"member":"Kate Hoey","dim1":4.2641,"dim2":-0.8783,"party":"Labour"},{"member":"Kate Hollern","dim1":16.0508,"dim2":3.1093,"party":"Labour"},{"member":"Kate Osamor","dim1":16.4565,"dim2":1.9451,"party":"Labour"},{"member":"Kathryn Clark","dim1":0.2528,"dim2":-0.1751,"party":"Labour"},{"member":"Keir Starmer","dim1":14.2085,"dim2":3.0677,"party":"Labour"},{"member":"Keith Simpson","dim1":-0.2306,"dim2":0.1796,"party":"Conservative"},{"member":"Keith Vaz","dim1":8.2536,"dim2":-0.7062,"party":"Labour"},{"member":"Kelly Tolhurst","dim1":-17.7616,"dim2":3.2638,"party":"Conservative"},{"member":"Kelvin Hopkins","dim1":11.6842,"dim2":-0.3462,"party":"Independent"},{"member":"Kenneth Clarke","dim1":-0.114,"dim2":0.1246,"party":"Conservative"},{"member":"Kerry McCarthy","dim1":16.2586,"dim2":1.3,"party":"Labour"},{"member":"Kevan Jones","dim1":0.2384,"dim2":-0.1093,"party":"Labour"},{"member":"Kevin Barron","dim1":3.8225,"dim2":-3.322,"party":"Labour"},{"member":"Kevin Brennan","dim1":16.368,"dim2":1.1935,"party":"Labour"},{"member":"Kevin Foster","dim1":-19.7389,"dim2":2.0774,"party":"Conservative"},{"member":"Kevin Hollinrake","dim1":-19.4418,"dim2":1.8666,"party":"Conservative"},{"member":"Khalid Mahmood","dim1":0.109,"dim2":-0.0101,"party":"Labour"},{"member":"Kirsten Oswald","dim1":5.8529,"dim2":-6.463,"party":"Scottish National Party"},{"member":"Kirstene Hair","dim1":-10.4701,"dim2":-7.9606,"party":"Conservative"},{"member":"Kirsty Blackman","dim1":14.7402,"dim2":0.9681,"party":"Scottish National Party"},{"member":"Kit Malthouse","dim1":-20.2682,"dim2":2.5379,"party":"Conservative"},{"member":"Kris Hopkins","dim1":-8.785,"dim2":9.7648,"party":"Conservative"},{"member":"Kwasi Kwarteng","dim1":-20.0312,"dim2":2.325,"party":"Conservative"},{"member":"Lady Hermon","dim1":8.7094,"dim2":3.207,"party":"Independent"},{"member":"Laura Pidcock","dim1":8.2951,"dim2":7.7801,"party":"Labour"},{"member":"Laura Sandys","dim1":-0.1587,"dim2":0.1523,"party":"Conservative"},{"member":"Laura Smith","dim1":9.1222,"dim2":8.9539,"party":"Labour"},{"member":"Laurence Robertson","dim1":-0.2528,"dim2":0.1751,"party":"Conservative"},{"member":"Layla Moran","dim1":8.3497,"dim2":7.8207,"party":"Liberal Democrat"},{"member":"Lee Rowley","dim1":-10.4209,"dim2":-8.028,"party":"Conservative"},{"member":"Lee Scott","dim1":-0.2306,"dim2":0.1796,"party":"Conservative"},{"member":"Leo Docherty","dim1":-10.5122,"dim2":-8.1176,"party":"Conservative"},{"member":"Lesley Laird","dim1":9.3107,"dim2":9.1871,"party":"Labour"},{"member":"Liam Byrne","dim1":14.1198,"dim2":3.5324,"party":"Labour"},{"member":"Liam Fox","dim1":-0.2139,"dim2":0.1559,"party":"Conservative"},{"member":"Lilian Greenwood","dim1":15.6237,"dim2":3.5778,"party":"Labour"},{"member":"Linda Riordan","dim1":0.109,"dim2":-0.0101,"party":"Labour"},{"member":"Lindsay Hoyle","dim1":0.109,"dim2":-0.0101,"party":"Chairman of Ways and Means"},{"member":"Lindsay Roy","dim1":0.2384,"dim2":-0.1093,"party":"Labour"},{"member":"Lisa Nandy","dim1":14.5509,"dim2":3.8916,"party":"Labour"},{"member":"Liz Kendall","dim1":15.8489,"dim2":3.5824,"party":"Labour"},{"member":"Liz McInnes","dim1":17.2117,"dim2":1.9859,"party":"Labour"},{"member":"Liz Saville Roberts","dim1":17.357,"dim2":-0.6408,"party":"Plaid Cymru"},{"member":"Liz Twist","dim1":9.0231,"dim2":9.0078,"party":"Labour"},{"member":"Lloyd Russell-Moyle","dim1":9.107,"dim2":8.8392,"party":"Labour"},{"member":"Lorely Burt","dim1":-0.0987,"dim2":0.082,"party":"Liberal Democrat"},{"member":"Lorraine Fullbrook","dim1":0.0352,"dim2":0.0171,"party":"Conservative"},{"member":"Louise Ellman","dim1":0.2384,"dim2":-0.1093,"party":"Labour"},{"member":"Louise Haigh","dim1":14.3442,"dim2":3.4766,"party":"Labour"},{"member":"Luciana Berger","dim1":10.5358,"dim2":-0.5544,"party":"Labour"},{"member":"Lucy Allan","dim1":-19.9905,"dim2":2.3246,"party":"Conservative"},{"member":"Lucy Frazer","dim1":-19.7727,"dim2":1.9947,"party":"Conservative"},{"member":"Lucy Powell","dim1":15.0354,"dim2":2.8308,"party":"Labour"},{"member":"Luke Graham","dim1":-10.3922,"dim2":-7.8527,"party":"Conservative"},{"member":"Luke Hall","dim1":-20.4971,"dim2":2.6959,"party":"Conservative"},{"member":"Luke Pollard","dim1":9.2583,"dim2":9.2383,"party":"Labour"},{"member":"Lyn Brown","dim1":16.6601,"dim2":2.5513,"party":"Labour"},{"member":"Lynne Featherstone","dim1":-0.0733,"dim2":0.1055,"party":"Liberal Democrat"},{"member":"Madeleine Moon","dim1":0.109,"dim2":-0.0101,"party":"Labour"},{"member":"Maggie Throup","dim1":-20.0669,"dim2":2.3084,"party":"Conservative"},{"member":"Malcolm Bruce","dim1":-0.114,"dim2":0.1246,"party":"Liberal Democrat"},{"member":"Malcolm Rifkind","dim1":0.0153,"dim2":0.0521,"party":"Conservative"},{"member":"Marcus Fysh","dim1":-8.5496,"dim2":9.3841,"party":"Conservative"},{"member":"Marcus Jones","dim1":-0.2306,"dim2":0.1796,"party":"Conservative"},{"member":"Marek Lazarowicz","dim1":0.2384,"dim2":-0.1093,"party":"Labour"},{"member":"Margaret Beckett","dim1":13.3763,"dim2":3.579,"party":"Labour"},{"member":"Margaret Begg","dim1":0.2384,"dim2":-0.1093,"party":"Labour"},{"member":"Margaret Coffey","dim1":0.2384,"dim2":-0.1093,"party":"Labour"},{"member":"Margaret Curran","dim1":0.2384,"dim2":-0.1093,"party":"Labour"},{"member":"Margaret Ferrier","dim1":6.7671,"dim2":-7.3933,"party":"Scottish National Party"},{"member":"Margaret Greenwood","dim1":16.9101,"dim2":2.2799,"party":"Labour"},{"member":"Margaret Hillier","dim1":0.2384,"dim2":-0.1093,"party":"Labour"},{"member":"Margaret Hodge","dim1":0.2384,"dim2":-0.1093,"party":"Labour"},{"member":"Margaret Munn","dim1":0.2384,"dim2":-0.1093,"party":"Labour"},{"member":"Margaret Ritchie","dim1":0.1523,"dim2":-0.0433,"party":"Social Democratic & Labour Party"},{"member":"Margot James","dim1":-18.2183,"dim2":1.2334,"party":"Conservative"},{"member":"Maria Caulfield","dim1":-20.4154,"dim2":2.5423,"party":"Conservative"},{"member":"Maria Eagle","dim1":15.5794,"dim2":3.6363,"party":"Labour"},{"member":"Maria Miller","dim1":-0.2528,"dim2":0.1751,"party":"Conservative"},{"member":"Marie Rimmer","dim1":6.1325,"dim2":-5.431,"party":"Labour"},{"member":"Marion Fellows","dim1":9.2146,"dim2":-0.1888,"party":"Scottish National Party"},{"member":"Mark Durkan","dim1":8.4558,"dim2":-9.0542,"party":"Social Democratic & Labour Party"},{"member":"Mark Field","dim1":-19.5316,"dim2":2.6559,"party":"Conservative"},{"member":"Mark Francois","dim1":-0.2528,"dim2":0.1751,"party":"Conservative"},{"member":"Mark Garnier","dim1":-19.8614,"dim2":2.0492,"party":"Conservative"},{"member":"Mark Harper","dim1":-0.2528,"dim2":0.1751,"party":"Conservative"},{"member":"Mark Hendrick","dim1":0.1521,"dim2":-0.0422,"party":"Labour"},{"member":"Mark Hoban","dim1":-0.2528,"dim2":0.1751,"party":"Conservative"},{"member":"Mark Hunter","dim1":-0.2219,"dim2":0.1713,"party":"Liberal Democrat"},{"member":"Mark Lancaster","dim1":-19.2785,"dim2":2.2164,"party":"Conservative"},{"member":"Mark Menzies","dim1":-20.0234,"dim2":2.6269,"party":"Conservative"},{"member":"Mark Pawsey","dim1":-20.1241,"dim2":2.5939,"party":"Conservative"},{"member":"Mark Prisk","dim1":-0.2306,"dim2":0.1796,"party":"Conservative"},{"member":"Mark Pritchard","dim1":-15.8661,"dim2":0.3052,"party":"Conservative"},{"member":"Mark Simmonds","dim1":-0.1918,"dim2":0.1604,"party":"Conservative"},{"member":"Mark Spencer","dim1":-18.6115,"dim2":1.2857,"party":"Conservative"},{"member":"Mark Tami","dim1":16.9154,"dim2":2.655,"party":"Labour"},{"member":"Mark Williams","dim1":0.0679,"dim2":0.0134,"party":"Liberal Democrat"},{"member":"Marsha De Cordova","dim1":9.0965,"dim2":8.89,"party":"Labour"},{"member":"Martin Caton","dim1":0.2384,"dim2":-0.1093,"party":"Labour"},{"member":"Martin Docherty-Hughes","dim1":14.4979,"dim2":-0.7074,"party":"Scottish National Party"},{"member":"Martin Horwood","dim1":-0.0973,"dim2":0.1009,"party":"Liberal Democrat"},{"member":"Martin Vickers","dim1":-20.5015,"dim2":2.8868,"party":"Conservative"},{"member":"Martin Whitfield","dim1":9.0676,"dim2":8.8659,"party":"Labour"},{"member":"Martyn Day","dim1":15.4265,"dim2":-0.1341,"party":"Scottish National Party"},{"member":"Mary Creagh","dim1":13.7784,"dim2":3.5349,"party":"Labour"},{"member":"Mary Glindon","dim1":17.4629,"dim2":2.345,"party":"Labour"},{"member":"Mary MacLeod","dim1":-0.2528,"dim2":0.1751,"party":"Conservative"},{"member":"Mary Robinson","dim1":-19.8558,"dim2":2.0577,"party":"Conservative"},{"member":"Matt Hancock","dim1":-15.8202,"dim2":-2.0007,"party":"Conservative"},{"member":"Matt Rodda","dim1":9.1133,"dim2":8.9269,"party":"Labour"},{"member":"Matt Warman","dim1":-20.0197,"dim2":2.1879,"party":"Conservative"},{"member":"Matt Western","dim1":9.0191,"dim2":8.9007,"party":"Labour"},{"member":"Matthew Hancock","dim1":-3.3663,"dim2":3.9459,"party":"Conservative"},{"member":"Matthew Offord","dim1":-0.1896,"dim2":0.1561,"party":"Conservative"},{"member":"Matthew Pennycook","dim1":16.771,"dim2":3.2427,"party":"Labour"},{"member":"Meg Hillier","dim1":16.0571,"dim2":1.7324,"party":"Labour"},{"member":"Mel Stride","dim1":-20.0764,"dim2":3.1405,"party":"Conservative"},{"member":"Melanie Onn","dim1":16.9447,"dim2":2.3429,"party":"Labour"},{"member":"Mhairi Black","dim1":12.5794,"dim2":-0.8355,"party":"Scottish National Party"},{"member":"Micael Dugher","dim1":0.2384,"dim2":-0.1093,"party":"Labour"},{"member":"Michael Connarty","dim1":0.2384,"dim2":-0.1093,"party":"Labour"},{"member":"Michael Dugher","dim1":4.7982,"dim2":-3.7843,"party":"Labour"},{"member":"Michael Ellis","dim1":-20.673,"dim2":3.1374,"party":"Conservative"},{"member":"Michael Fabricant","dim1":-19.1635,"dim2":1.0836,"party":"Conservative"},{"member":"Michael Fallon","dim1":-3.6249,"dim2":4.0917,"party":"Conservative"},{"member":"Michael Gapes","dim1":0.2384,"dim2":-0.1093,"party":"Labour"},{"member":"Michael Gove","dim1":-18.5118,"dim2":1.0377,"party":"Conservative"},{"member":"Michael Hancock","dim1":-0.0278,"dim2":0.0681,"party":"Liberal Democrat"},{"member":"Michael McCann","dim1":0.2384,"dim2":-0.1093,"party":"Labour"},{"member":"Michael Meacher","dim1":0.109,"dim2":-0.0101,"party":"Labour"},{"member":"Michael Moore","dim1":-0.2219,"dim2":0.1713,"party":"Liberal Democrat"},{"member":"Michael Penning","dim1":-0.1728,"dim2":0.1324,"party":"Conservative"},{"member":"Michael Thornton","dim1":-0.0769,"dim2":0.1097,"party":"Liberal Democrat"},{"member":"Michael Tomlinson","dim1":-20.5186,"dim2":2.7305,"party":"Conservative"},{"member":"Michael Weir","dim1":0.2384,"dim2":-0.1093,"party":"Scottish National"},{"member":"Michael Wood","dim1":0.2384,"dim2":-0.1093,"party":"Labour"},{"member":"Michelle Donelan","dim1":-18.6504,"dim2":0.9466,"party":"Conservative"},{"member":"Michelle Gildernew","dim1":0.109,"dim2":-0.0101,"party":"Sinn Féin"},{"member":"Michelle Thomson","dim1":6.2107,"dim2":-6.9598,"party":"Independent"},{"member":"Mike  Crockart","dim1":0.0458,"dim2":0.0089,"party":"Liberal Democrat"},{"member":"Mike Amesbury","dim1":9.4179,"dim2":9.1064,"party":"Labour"},{"member":"Mike Freer","dim1":-18.3292,"dim2":2.5703,"party":"Conservative"},{"member":"Mike Gapes","dim1":16.3961,"dim2":2.3494,"party":"Labour"},{"member":"Mike Hill","dim1":9.1566,"dim2":9.0213,"party":"Labour"},{"member":"Mike Kane","dim1":16.4406,"dim2":2.3675,"party":"Labour"},{"member":"Mike Penning","dim1":-10.0529,"dim2":9.1811,"party":"Conservative"},{"member":"Mike Weatherley","dim1":-0.2528,"dim2":0.1751,"party":"Conservative"},{"member":"Mike Weir","dim1":6.5886,"dim2":-7.1364,"party":"Scottish National Party"},{"member":"Mike Wood","dim1":-17.2054,"dim2":-0.6084,"party":"Conservative"},{"member":"Mims Davies","dim1":-18.2526,"dim2":4.0053,"party":"Conservative"},{"member":"Mohammad Yasin","dim1":9.0014,"dim2":8.9353,"party":"Labour"},{"member":"Mr Adrian Bailey","dim1":15.0242,"dim2":2.5566,"party":"Labour"},{"member":"Mr Alan Campbell","dim1":17.3477,"dim2":2.3096,"party":"Labour"},{"member":"Mr Alan Mak","dim1":-9.1065,"dim2":9.904,"party":"Conservative"},{"member":"Mr Alistair Carmichael","dim1":14.5008,"dim2":1.2737,"party":"Liberal Democrat"},{"member":"Mr Alister Jack","dim1":-10.2198,"dim2":-7.951,"party":"Conservative"},{"member":"Mr Andrew Mitchell","dim1":-17.4786,"dim2":0.3831,"party":"Conservative"},{"member":"Mr Andrew Smith","dim1":7.7615,"dim2":-6.5094,"party":"Labour"},{"member":"Mr Andrew Turner","dim1":-9.4993,"dim2":10.2442,"party":"Conservative"},{"member":"Mr Andrew Tyrie","dim1":-7.7351,"dim2":8.1762,"party":"Conservative"},{"member":"Mr Barry Sheerman","dim1":15.866,"dim2":2.9493,"party":"Labour"},{"member":"Mr Ben  Wallace","dim1":-5.4735,"dim2":-4.3,"party":"Conservative"},{"member":"Mr Ben Bradshaw","dim1":16.7837,"dim2":2.3088,"party":"Labour"},{"member":"Mr Ben Wallace","dim1":-12.6326,"dim2":4.9069,"party":"Conservative"},{"member":"Mr Bernard Jenkin","dim1":-16.0385,"dim2":2.9022,"party":"Conservative"},{"member":"Mr Bob Seely","dim1":-10.1352,"dim2":-8.151,"party":"Conservative"},{"member":"Mr Charles Walker","dim1":-18.3101,"dim2":1.0762,"party":"Conservative"},{"member":"Mr Chris Leslie","dim1":8.9233,"dim2":8.7731,"party":"Labour"},{"member":"Mr Christopher Chope","dim1":-12.1408,"dim2":5.7164,"party":"Conservative"},{"member":"Mr Chuka Umunna","dim1":6.2082,"dim2":-5.1985,"party":"Labour"},{"member":"Mr Clive Betts","dim1":14.7389,"dim2":3.4231,"party":"Labour"},{"member":"Mr Damian Hinds","dim1":-6.1451,"dim2":-4.5557,"party":"Conservative"},{"member":"Mr David Anderson","dim1":5.563,"dim2":-4.5885,"party":"Labour"},{"member":"Mr David Burrowes","dim1":-8.829,"dim2":9.6189,"party":"Conservative"},{"member":"Mr David Cameron","dim1":-0.6496,"dim2":0.7648,"party":"Conservative"},{"member":"Mr David Crausby","dim1":2.428,"dim2":-2.0805,"party":"Labour"},{"member":"Mr David Davis","dim1":-15.1837,"dim2":-0.293,"party":"Conservative"},{"member":"Mr David Gauke","dim1":-18.9604,"dim2":1.2803,"party":"Conservative"},{"member":"Mr David Hanson","dim1":7.4871,"dim2":-6.2264,"party":"Labour"},{"member":"Mr David Jones","dim1":-19.0236,"dim2":1.5785,"party":"Conservative"},{"member":"Mr David Lammy","dim1":14.5836,"dim2":2.4932,"party":"Labour"},{"member":"Mr David Lidington","dim1":-19.1388,"dim2":1.7888,"party":"Conservative"},{"member":"Mr David Nuttall","dim1":-8.7167,"dim2":9.5725,"party":"Conservative"},{"member":"Mr David Winnick","dim1":8.005,"dim2":-7.0632,"party":"Labour"},{"member":"Mr Dennis Skinner","dim1":17.1457,"dim2":-0.3115,"party":"Labour"},{"member":"Mr Desmond Swayne","dim1":-2.9169,"dim2":3.399,"party":"Conservative"},{"member":"Mr Dominic Grieve","dim1":-17.863,"dim2":2.79,"party":"Conservative"},{"member":"Mr Douglas Carswell","dim1":-1.9213,"dim2":2.2467,"party":"UK Independence Party"},{"member":"Mr Edward Vaizey","dim1":-17.223,"dim2":1.6978,"party":"Conservative"},{"member":"Mr Gary Streeter","dim1":-15.219,"dim2":6.1015,"party":"Conservative"},{"member":"Mr Gavin Shuker","dim1":14.96,"dim2":3.085,"party":"Labour"},{"member":"Mr Geoffrey Cox","dim1":-17.9297,"dim2":0.4463,"party":"Conservative"},{"member":"Mr Geoffrey Robinson","dim1":14.0995,"dim2":0.8146,"party":"Labour"},{"member":"Mr George Howarth","dim1":13.5496,"dim2":3.4823,"party":"Labour"},{"member":"Mr George Osborne","dim1":-4.4651,"dim2":4.8862,"party":"Conservative"},{"member":"Mr Graham Allen","dim1":4.0887,"dim2":-3.7905,"party":"Labour"},{"member":"Mr Graham Brady","dim1":-12.6545,"dim2":6.1596,"party":"Conservative"},{"member":"Mr Gregory Campbell","dim1":-12.5491,"dim2":-2.3926,"party":"Democratic Unionist Party"},{"member":"Mr Hugo Swire","dim1":-3.1062,"dim2":3.7815,"party":"Conservative"},{"member":"Mr Iain Duncan Smith","dim1":-19.2185,"dim2":1.8809,"party":"Conservative"},{"member":"Mr Iain Wright","dim1":7.4197,"dim2":-5.9937,"party":"Labour"},{"member":"Mr Ian Liddell-Grainger","dim1":-15.8458,"dim2":2.2406,"party":"Conservative"},{"member":"Mr Ivan Lewis","dim1":10.4542,"dim2":2.829,"party":"Independent"},{"member":"Mr Jacob Rees-Mogg","dim1":-20.1335,"dim2":2.4591,"party":"Conservative"},{"member":"Mr Jamie Reed","dim1":3.7441,"dim2":-3.1503,"party":"Labour"},{"member":"Mr Jeffrey M. Donaldson","dim1":-0.6527,"dim2":0.8817,"party":"Democratic Unionist Party"},{"member":"Mr Jeremy Hunt","dim1":-18.7372,"dim2":1.6499,"party":"Conservative"},{"member":"Mr Jim Cunningham","dim1":17.6995,"dim2":2.2026,"party":"Labour"},{"member":"Mr John Baron","dim1":-16.3075,"dim2":-1.3921,"party":"Conservative"},{"member":"Mr John Hayes","dim1":-19.0409,"dim2":1.2313,"party":"Conservative"},{"member":"Mr John Whittingdale","dim1":-19.3222,"dim2":2.2842,"party":"Conservative"},{"member":"Mr Jonathan Djanogly","dim1":-18.8318,"dim2":2.3343,"party":"Conservative"},{"member":"Mr Jonathan Lord","dim1":-17.5884,"dim2":1.074,"party":"Conservative"},{"member":"Mr Julian Brazier","dim1":-6.0098,"dim2":6.8136,"party":"Conservative"},{"member":"Mr Keith Simpson","dim1":-19.3053,"dim2":2.5366,"party":"Conservative"},{"member":"Mr Kenneth Clarke","dim1":-9.3368,"dim2":2.9066,"party":"Conservative"},{"member":"Mr Kevan Jones","dim1":15.51,"dim2":2.7985,"party":"Labour"},{"member":"Mr Khalid Mahmood","dim1":14.4839,"dim2":3.584,"party":"Labour"},{"member":"Mr Laurence Robertson","dim1":-18.7584,"dim2":0.9333,"party":"Conservative"},{"member":"Mr Marcus Fysh","dim1":-10.4057,"dim2":-7.8968,"party":"Conservative"},{"member":"Mr Marcus Jones","dim1":-20.2409,"dim2":2.4171,"party":"Conservative"},{"member":"Mr Mark Francois","dim1":-17.8671,"dim2":0.9319,"party":"Conservative"},{"member":"Mr Mark Harper","dim1":-19.9609,"dim2":2.4329,"party":"Conservative"},{"member":"Mr Mark Hendrick","dim1":9.1601,"dim2":-1.0049,"party":"Labour"},{"member":"Mr Mark Prisk","dim1":-18.6235,"dim2":1.0443,"party":"Conservative"},{"member":"Mr Mark Williams","dim1":6.6248,"dim2":-6.644,"party":"Liberal Democrat"},{"member":"Mr Nicholas Brown","dim1":17.2519,"dim2":2.7373,"party":"Labour"},{"member":"Mr Nick  Hurd","dim1":-1.3817,"dim2":-1.2441,"party":"Conservative"},{"member":"Mr Nick Clegg","dim1":4.3424,"dim2":-4.6043,"party":"Liberal Democrat"},{"member":"Mr Nick Hurd","dim1":-16.6614,"dim2":1.6922,"party":"Conservative"},{"member":"Mr Nigel Dodds","dim1":-4.0567,"dim2":5.0262,"party":"Democratic Unionist Party"},{"member":"Mr Nigel Evans","dim1":-16.5136,"dim2":1.31,"party":"Conservative"},{"member":"Mr Oliver Letwin","dim1":-3.8864,"dim2":4.5746,"party":"Conservative"},{"member":"Mr Owen Paterson","dim1":-16.8641,"dim2":2.1854,"party":"Conservative"},{"member":"Mr Pat McFadden","dim1":15.8926,"dim2":2.8352,"party":"Labour"},{"member":"Mr Patrick McLoughlin","dim1":-3.2644,"dim2":3.5671,"party":"Conservative"},{"member":"Mr Paul J Sweeney","dim1":1.5357,"dim2":1.2811,"party":"Labour"},{"member":"Mr Paul Sweeney","dim1":7.478,"dim2":7.5278,"party":"Labour"},{"member":"Mr Peter Bone","dim1":-19.27,"dim2":2.2562,"party":"Conservative"},{"member":"Mr Peter Lilley","dim1":-7.7999,"dim2":8.4913,"party":"Conservative"},{"member":"Mr Philip Dunne","dim1":-19.8217,"dim2":2.1817,"party":"Conservative"},{"member":"Mr Philip Hammond","dim1":-13.0464,"dim2":-2.3667,"party":"Conservative"},{"member":"Mr Philip Hollobone","dim1":-18.9173,"dim2":2.1286,"party":"Conservative"},{"member":"Mr Ranil Jayawardena","dim1":-18.6411,"dim2":1.3347,"party":"Conservative"},{"member":"Mr Richard Bacon","dim1":-18.9233,"dim2":1.6273,"party":"Conservative"},{"member":"Mr Rob Wilson","dim1":-9.2644,"dim2":9.9604,"party":"Conservative"},{"member":"Mr Robert Goodwill","dim1":-19.8405,"dim2":2.3426,"party":"Conservative"},{"member":"Mr Robert Syms","dim1":-10.4956,"dim2":9.6268,"party":"Conservative"},{"member":"Mr Robin Walker","dim1":-19.6083,"dim2":2.2416,"party":"Conservative"},{"member":"Mr Roger Godsiff","dim1":13.5304,"dim2":2.4556,"party":"Labour"},{"member":"Mr Ronnie Campbell","dim1":11.8855,"dim2":2.2923,"party":"Labour"},{"member":"Mr Sam Gyimah","dim1":-19.9041,"dim2":2.283,"party":"Conservative"},{"member":"Mr Shailesh Vara","dim1":-20.1569,"dim2":2.4259,"party":"Conservative"},{"member":"Mr Simon Clarke","dim1":-10.4381,"dim2":-8.0693,"party":"Conservative"},{"member":"Mr Stephen Hepburn","dim1":15.2046,"dim2":3.8502,"party":"Labour"},{"member":"Mr Steve Baker","dim1":-20.0672,"dim2":1.9245,"party":"Conservative"},{"member":"Mr Steve Reed","dim1":16.1781,"dim2":3.1924,"party":"Labour"},{"member":"Mr Stewart Jackson","dim1":-9.0748,"dim2":9.8513,"party":"Conservative"},{"member":"Mr Tanmanjeet Singh Dhesi","dim1":9.1082,"dim2":8.8909,"party":"Labour"},{"member":"Mr Tobias Ellwood","dim1":-18.9998,"dim2":1.0928,"party":"Conservative"},{"member":"Mr Virendra Sharma","dim1":12.9181,"dim2":2.4075,"party":"Labour"},{"member":"Mr William Wragg","dim1":-10.7102,"dim2":-7.807,"party":"Conservative"},{"member":"Mrs Anne Main","dim1":-18.5167,"dim2":1.5354,"party":"Conservative"},{"member":"Mrs Anne-Marie Trevelyan","dim1":-19.7126,"dim2":2.0322,"party":"Conservative"},{"member":"Mrs Caroline Spelman","dim1":-3.6342,"dim2":4.0649,"party":"Conservative"},{"member":"Mrs Cheryl Gillan","dim1":-11.8711,"dim2":5.534,"party":"Conservative"},{"member":"Mrs Emma Lewell-Buck","dim1":15.6649,"dim2":1.964,"party":"Labour"},{"member":"Mrs Flick Drummond","dim1":-9.7781,"dim2":10.7976,"party":"Conservative"},{"member":"Mrs Heather Wheeler","dim1":-7.8129,"dim2":-6.2949,"party":"Conservative"},{"member":"Mrs Helen Grant","dim1":-19.7275,"dim2":2.0142,"party":"Conservative"},{"member":"Mrs Kemi Badenoch","dim1":-10.5793,"dim2":-8.1098,"party":"Conservative"},{"member":"Mrs Louise Ellman","dim1":15.4594,"dim2":-0.7553,"party":"Labour"},{"member":"Mrs Madeleine Moon","dim1":13.0656,"dim2":2.7055,"party":"Labour"},{"member":"Mrs Maria Miller","dim1":-19.3785,"dim2":2.0111,"party":"Conservative"},{"member":"Mrs Pauline Latham","dim1":-9.9211,"dim2":-7.5431,"party":"Conservative"},{"member":"Mrs Sharon Hodgson","dim1":17.0313,"dim2":2.8277,"party":"Labour"},{"member":"Mrs Sheryll Murray","dim1":-20.1522,"dim2":2.5144,"party":"Conservative"},{"member":"Mrs Theresa May","dim1":-10.2946,"dim2":1.7481,"party":"Conservative"},{"member":"Mrs Theresa Villiers","dim1":-8.1888,"dim2":8.9317,"party":"Conservative"},{"member":"Ms Angela Eagle","dim1":15.6695,"dim2":2.8815,"party":"Labour"},{"member":"Ms Diane Abbott","dim1":16.4055,"dim2":2.8005,"party":"Labour"},{"member":"Ms Gisela Stuart","dim1":4.6273,"dim2":-3.5944,"party":"Labour"},{"member":"Ms Harriet Harman","dim1":12.8873,"dim2":4.1385,"party":"Labour"},{"member":"Ms Karen Buck","dim1":16.771,"dim2":1.7905,"party":"Labour"},{"member":"Ms Karen Lee","dim1":4.3907,"dim2":3.9369,"party":"Labour"},{"member":"Ms Margaret Ritchie","dim1":8.5384,"dim2":-9.195,"party":"Social Democratic & Labour Party"},{"member":"Ms Marie Rimmer","dim1":9.4427,"dim2":7.9374,"party":"Labour"},{"member":"Ms Nadine Dorries","dim1":-8.9643,"dim2":-6.6509,"party":"Conservative"},{"member":"Ms Nusrat Ghani","dim1":-10.7081,"dim2":-7.9206,"party":"Conservative"},{"member":"Ms Tasmina Ahmed-Sheikh","dim1":6.2881,"dim2":-6.9313,"party":"Scottish National Party"},{"member":"Nadhim Zahawi","dim1":-18.7438,"dim2":0.9299,"party":"Conservative"},{"member":"Nadine Dorries","dim1":-4.3058,"dim2":4.6789,"party":"Conservative"},{"member":"Naomi Long","dim1":0.0615,"dim2":0.0199,"party":"Alliance"},{"member":"Natalie McGarry","dim1":5.7428,"dim2":-6.3239,"party":"Independent"},{"member":"Natascha Engel","dim1":0.2384,"dim2":-0.1093,"party":"Labour"},{"member":"Naz Shah","dim1":14.1792,"dim2":3.5573,"party":"Labour"},{"member":"Neil Carmichael","dim1":-9.1004,"dim2":10.1093,"party":"Conservative"},{"member":"Neil Coyle","dim1":17.0513,"dim2":2.0858,"party":"Labour"},{"member":"Neil Gray","dim1":14.8486,"dim2":-0.2153,"party":"Scottish National Party"},{"member":"Neil O'Brien","dim1":-9.8428,"dim2":-7.9646,"party":"Conservative"},{"member":"Neil Parish","dim1":-19.2994,"dim2":1.5598,"party":"Conservative"},{"member":"Nia Griffith","dim1":16.6619,"dim2":3.4022,"party":"Labour"},{"member":"Nic Dakin","dim1":14.7904,"dim2":1.7518,"party":"Labour"},{"member":"Nicholas Brown","dim1":0.2384,"dim2":-0.1093,"party":"Labour"},{"member":"Nicholas Clegg","dim1":0.109,"dim2":-0.0101,"party":"Liberal Democrat"},{"member":"Nicholas Harvey","dim1":-0.1568,"dim2":0.1525,"party":"Liberal Democrat"},{"member":"Nicholas Herbert","dim1":-0.1896,"dim2":0.1561,"party":"Conservative"},{"member":"Nicholas Hurd","dim1":-0.2219,"dim2":0.1713,"party":"Conservative"},{"member":"Nick Boles","dim1":-15.4698,"dim2":-1.3937,"party":"Conservative"},{"member":"Nick Dakin","dim1":0.1964,"dim2":-0.0859,"party":"Labour"},{"member":"Nick de Bois","dim1":-0.1551,"dim2":0.1481,"party":"Conservative"},{"member":"Nick Gibb","dim1":-19.6838,"dim2":2.9913,"party":"Conservative"},{"member":"Nick Herbert","dim1":-16.7454,"dim2":0.339,"party":"Conservative"},{"member":"Nick Smith","dim1":13.8304,"dim2":2.047,"party":"Labour"},{"member":"Nick Thomas-Symonds","dim1":15.5282,"dim2":3.8808,"party":"Labour"},{"member":"Nicky Morgan","dim1":-18.2534,"dim2":2.3205,"party":"Conservative"},{"member":"Nicola Blackwood","dim1":-7.541,"dim2":7.922,"party":"Conservative"},{"member":"Nicolas Gibb","dim1":-0.2306,"dim2":0.1796,"party":"Conservative"},{"member":"Nigel Adams","dim1":-17.3901,"dim2":2.6618,"party":"Conservative"},{"member":"Nigel Dodds","dim1":-10.14,"dim2":-7.4006,"party":"Democratic Unionist Party"},{"member":"Nigel Evans","dim1":-0.2528,"dim2":0.1751,"party":"First Deputy Chairman of Ways and Means"},{"member":"Nigel Huddleston","dim1":-20.097,"dim2":2.6708,"party":"Conservative"},{"member":"Nigel Mills","dim1":-19.7634,"dim2":2.4527,"party":"Conservative"},{"member":"Norman Baker","dim1":-0.099,"dim2":0.1053,"party":"Liberal Democrat"},{"member":"Norman Lamb","dim1":14.0933,"dim2":0.4716,"party":"Liberal Democrat"},{"member":"Nusrat Ghani","dim1":-9.1555,"dim2":10.1542,"party":"Conservative"},{"member":"Oliver Colvile","dim1":-9.4339,"dim2":10.3125,"party":"Conservative"},{"member":"Oliver Dowden","dim1":-19.9591,"dim2":2.1532,"party":"Conservative"},{"member":"Oliver Heald","dim1":-0.2528,"dim2":0.1751,"party":"Conservative"},{"member":"Oliver Letwin","dim1":-0.1507,"dim2":0.1369,"party":"Conservative"},{"member":"Owen Paterson","dim1":-0.0322,"dim2":0.0821,"party":"Conservative"},{"member":"Owen Smith","dim1":15.0692,"dim2":3.2049,"party":"Labour"},{"member":"Owen Thompson","dim1":4.5666,"dim2":-4.398,"party":"Scottish National Party"},{"member":"Pamela Nash","dim1":0.2384,"dim2":-0.1093,"party":"Labour"},{"member":"Pat Doherty","dim1":0.109,"dim2":-0.0101,"party":"Sinn Féin"},{"member":"Pat Glass","dim1":6.2787,"dim2":-5.3473,"party":"Labour"},{"member":"Patricia Gibson","dim1":15.8236,"dim2":-0.6877,"party":"Scottish National Party"},{"member":"Patrick Grady","dim1":15.474,"dim2":-0.4361,"party":"Scottish National Party"},{"member":"Patrick McFadden","dim1":0.2384,"dim2":-0.1093,"party":"Labour"},{"member":"Patrick McLoughlin","dim1":-0.1384,"dim2":0.1244,"party":"Conservative"},{"member":"Paul Blomfield","dim1":17.4078,"dim2":2.5096,"party":"Labour"},{"member":"Paul Burstow","dim1":-0.2219,"dim2":0.1713,"party":"Liberal Democrat"},{"member":"Paul Farrelly","dim1":14.923,"dim2":2.9381,"party":"Labour"},{"member":"Paul Flynn","dim1":14.0266,"dim2":-1.2468,"party":"Labour"},{"member":"Paul Girvan","dim1":-10.0869,"dim2":-7.6888,"party":"Democratic Unionist Party"},{"member":"Paul Maskey","dim1":0.109,"dim2":-0.0101,"party":"Sinn Féin"},{"member":"Paul Masterton","dim1":-9.9917,"dim2":-7.48,"party":"Conservative"},{"member":"Paul Maynard","dim1":-19.2841,"dim2":3.5555,"party":"Conservative"},{"member":"Paul Murphy","dim1":0.2384,"dim2":-0.1093,"party":"Labour"},{"member":"Paul Scully","dim1":-19.0765,"dim2":1.889,"party":"Conservative"},{"member":"Paul Uppal","dim1":-0.2528,"dim2":0.1751,"party":"Conservative"},{"member":"Paula Sherriff","dim1":16.8836,"dim2":2.9105,"party":"Labour"},{"member":"Pauline Latham","dim1":-8.8979,"dim2":9.7095,"party":"Conservative"},{"member":"Penny Mordaunt","dim1":-20.2853,"dim2":2.9073,"party":"Conservative"},{"member":"Pete Wishart","dim1":14.6827,"dim2":0.2172,"party":"Scottish National Party"},{"member":"Peter Aldous","dim1":-20.6338,"dim2":3.0958,"party":"Conservative"},{"member":"Peter Bone","dim1":-0.2219,"dim2":0.1713,"party":"Conservative"},{"member":"Peter Bottomley","dim1":-0.2528,"dim2":0.1751,"party":"Conservative"},{"member":"Peter Dowd","dim1":16.7678,"dim2":3.1668,"party":"Labour"},{"member":"Peter Grant","dim1":15.6909,"dim2":-0.0234,"party":"Scottish National Party"},{"member":"Peter Hain","dim1":0.2384,"dim2":-0.1093,"party":"Labour"},{"member":"Peter Heaton-Jones","dim1":-20.2301,"dim2":2.736,"party":"Conservative"},{"member":"Peter Kyle","dim1":17.0032,"dim2":1.9844,"party":"Labour"},{"member":"Peter Lilley","dim1":-0.2528,"dim2":0.1751,"party":"Conservative"},{"member":"Peter Luff","dim1":-0.2117,"dim2":0.1517,"party":"Conservative"},{"member":"Peter Tapsell","dim1":-0.1744,"dim2":0.1414,"party":"Conservative"},{"member":"Peter Wishart","dim1":0.1951,"dim2":-0.0761,"party":"Scottish National"},{"member":"Phil Wilson","dim1":14.726,"dim2":3.5725,"party":"Labour"},{"member":"Philip Boswell","dim1":7.2048,"dim2":-8.0107,"party":"Scottish National Party"},{"member":"Philip Davies","dim1":-13.4745,"dim2":-2.0677,"party":"Conservative"},{"member":"Philip Dunne","dim1":-0.1587,"dim2":0.1523,"party":"Conservative"},{"member":"Philip Hammond","dim1":0.0272,"dim2":0.0325,"party":"Conservative"},{"member":"Philip Hollobone","dim1":-0.2219,"dim2":0.1713,"party":"Conservative"},{"member":"Philip Wilson","dim1":0.1729,"dim2":-0.0628,"party":"Labour"},{"member":"Phillip Lee","dim1":-0.1998,"dim2":0.1758,"party":"Conservative"},{"member":"Preet Gill","dim1":0.2249,"dim2":0.1771,"party":"Labour"},{"member":"Preet Kaur Gill","dim1":8.9112,"dim2":8.6914,"party":"Labour"},{"member":"Priti Patel","dim1":-18.6084,"dim2":1.3722,"party":"Conservative"},{"member":"Rachael Maskell","dim1":18.1392,"dim2":1.3679,"party":"Labour"},{"member":"Rachel Maclean","dim1":-10.3455,"dim2":-7.9011,"party":"Conservative"},{"member":"Rachel Reeves","dim1":14.7176,"dim2":3.2696,"party":"Labour"},{"member":"Rebecca Harris","dim1":-20.5118,"dim2":3.174,"party":"Conservative"},{"member":"Rebecca Long Bailey","dim1":16.574,"dim2":2.3842,"party":"Labour"},{"member":"Rebecca Pow","dim1":-18.6277,"dim2":2.3407,"party":"Conservative"},{"member":"Rehman Chishti","dim1":-19.3994,"dim2":2.2306,"party":"Conservative"},{"member":"Richard Arkless","dim1":5.7216,"dim2":-6.1758,"party":"Scottish National Party"},{"member":"Richard Bacon","dim1":-0.1077,"dim2":0.1135,"party":"Conservative"},{"member":"Richard Benyon","dim1":-17.1803,"dim2":2.3086,"party":"Conservative"},{"member":"Richard Burden","dim1":14.285,"dim2":3.829,"party":"Labour"},{"member":"Richard Burgon","dim1":16.9622,"dim2":2.142,"party":"Labour"},{"member":"Richard Drax","dim1":-19.8465,"dim2":2.1962,"party":"Conservative"},{"member":"Richard Fuller","dim1":-9.369,"dim2":10.1787,"party":"Conservative"},{"member":"Richard Graham","dim1":-19.4252,"dim2":1.733,"party":"Conservative"},{"member":"Richard Harrington","dim1":-19.3399,"dim2":2.334,"party":"Conservative"},{"member":"Richard Ottaway","dim1":-0.2306,"dim2":0.1796,"party":"Conservative"},{"member":"Richard Shepherd","dim1":0.0291,"dim2":0.0326,"party":"Conservative"},{"member":"Rishi Sunak","dim1":-20.3208,"dim2":2.7447,"party":"Conservative"},{"member":"Rob Marris","dim1":7.1661,"dim2":-5.8966,"party":"Labour"},{"member":"Robert Ainsworth","dim1":0.109,"dim2":-0.0101,"party":"Labour"},{"member":"Robert Buckland","dim1":-19.8659,"dim2":2.1952,"party":"Conservative"},{"member":"Robert Courts","dim1":-15.3247,"dim2":-3.1686,"party":"Conservative"},{"member":"Robert Flello","dim1":6.9043,"dim2":-5.523,"party":"Labour"},{"member":"Robert Goodwill","dim1":-0.2528,"dim2":0.1751,"party":"Conservative"},{"member":"Robert Halfon","dim1":-20.1638,"dim2":2.4026,"party":"Conservative"},{"member":"Robert Jenrick","dim1":-20.0438,"dim2":2.5353,"party":"Conservative"},{"member":"Robert McCrea","dim1":-0.0286,"dim2":0.0738,"party":"Democratic Unionist"},{"member":"Robert Neill","dim1":-18.6519,"dim2":2.1995,"party":"Conservative"},{"member":"Robert Russell","dim1":-0.1808,"dim2":0.1479,"party":"Liberal Democrat"},{"member":"Robert Smith","dim1":-0.2219,"dim2":0.1713,"party":"Liberal Democrat"},{"member":"Robert Stunell","dim1":-0.2219,"dim2":0.1713,"party":"Liberal Democrat"},{"member":"Robert Syms","dim1":-0.2528,"dim2":0.1751,"party":"Conservative"},{"member":"Robert Wallace","dim1":-0.2057,"dim2":0.1444,"party":"Conservative"},{"member":"Robert Walter","dim1":0.109,"dim2":-0.0101,"party":"Conservative"},{"member":"Robert Wilson","dim1":-0.2306,"dim2":0.1796,"party":"Conservative"},{"member":"Roberta Blackman-Woods","dim1":0.2384,"dim2":-0.1093,"party":"Labour"},{"member":"Robin Walker","dim1":-0.2528,"dim2":0.1751,"party":"Conservative"},{"member":"Roger Gale","dim1":0.0272,"dim2":0.0325,"party":"Conservative"},{"member":"Roger Godsiff","dim1":0.2528,"dim2":-0.1751,"party":"Labour"},{"member":"Roger Mullin","dim1":7.2025,"dim2":-7.8599,"party":"Scottish National Party"},{"member":"Roger Williams","dim1":-0.1551,"dim2":0.1481,"party":"Liberal Democrat"},{"member":"Ronald Campbell","dim1":0.2384,"dim2":-0.1093,"party":"Labour"},{"member":"Ronnie Cowan","dim1":14.459,"dim2":-0.9597,"party":"Scottish National Party"},{"member":"Rory Stewart","dim1":-19.7999,"dim2":2.3043,"party":"Conservative"},{"member":"Rosalie Winterton","dim1":0.2384,"dim2":-0.1093,"party":"Labour"},{"member":"Rosemary Cooper","dim1":0.2384,"dim2":-0.1093,"party":"Labour"},{"member":"Rosie Cooper","dim1":13.553,"dim2":4.5643,"party":"Labour"},{"member":"Rosie Duffield","dim1":9.4357,"dim2":9.2674,"party":"Labour"},{"member":"Ross Thomson","dim1":-10.5558,"dim2":-8.1623,"party":"Conservative"},{"member":"Royston Smith","dim1":-20.0625,"dim2":2.7804,"party":"Conservative"},{"member":"Rushanara Ali","dim1":16.9615,"dim2":2.5176,"party":"Labour"},{"member":"Russell Brown","dim1":0.2384,"dim2":-0.1093,"party":"Labour"},{"member":"Ruth Cadbury","dim1":16.8718,"dim2":2.5342,"party":"Labour"},{"member":"Ruth George","dim1":9.2872,"dim2":8.643,"party":"Labour"},{"member":"Ruth Smeeth","dim1":15.0566,"dim2":4.4102,"party":"Labour"},{"member":"Sadiq Khan","dim1":0.6266,"dim2":-0.5019,"party":"Labour"},{"member":"Sajid Javid","dim1":-18.8317,"dim2":1.9324,"party":"Conservative"},{"member":"Sam Gyimah","dim1":-0.2528,"dim2":0.1751,"party":"Conservative"},{"member":"Sammy  Wilson","dim1":-1.3247,"dim2":-1.1804,"party":"Democratic Unionist Party"},{"member":"Sammy Wilson","dim1":-11.9039,"dim2":-2.2348,"party":"Democratic Unionist Party"},{"member":"Sandra Osborne","dim1":0.2384,"dim2":-0.1093,"party":"Labour"},{"member":"Sandy Martin","dim1":9.4432,"dim2":9.3134,"party":"Labour"},{"member":"Sarah Champion","dim1":15.2963,"dim2":2.1395,"party":"Labour"},{"member":"Sarah Jones","dim1":9.1907,"dim2":9.0066,"party":"Labour"},{"member":"Sarah Newton","dim1":-19,"dim2":1.0227,"party":"Conservative"},{"member":"Sarah Olney","dim1":2.9479,"dim2":-2.8361,"party":"Liberal Democrat"},{"member":"Sarah Teather","dim1":-0.1587,"dim2":0.1523,"party":"Liberal Democrat"},{"member":"Sarah Wollaston","dim1":-0.1609,"dim2":0.1565,"party":"Conservative"},{"member":"Scott Mann","dim1":-20.048,"dim2":2.3132,"party":"Conservative"},{"member":"Seema Kennedy","dim1":-19.7183,"dim2":2.5977,"party":"Conservative"},{"member":"Seema Malhotra","dim1":16.626,"dim2":2.5619,"party":"Labour"},{"member":"Shabana Mahmood","dim1":14.5082,"dim2":2.9987,"party":"Labour"},{"member":"Shailesh Vara","dim1":-0.2528,"dim2":0.1751,"party":"Conservative"},{"member":"Sharon Hodgson","dim1":0.109,"dim2":-0.0101,"party":"Labour"},{"member":"Shaun Woodward","dim1":0.2384,"dim2":-0.1093,"party":"Labour"},{"member":"Sheila  Gilmore","dim1":0.2384,"dim2":-0.1093,"party":"Labour"},{"member":"Sheryll Murray","dim1":-0.2219,"dim2":0.1713,"party":"Conservative"},{"member":"Siân James","dim1":0.109,"dim2":-0.0101,"party":"Labour"},{"member":"Simon  Danczuk","dim1":0.2384,"dim2":-0.1093,"party":"Labour"},{"member":"Simon Burns","dim1":-0.2528,"dim2":0.1751,"party":"Conservative"},{"member":"Simon Danczuk","dim1":6.4575,"dim2":-5.2768,"party":"Independent"},{"member":"Simon Hart","dim1":-19.3034,"dim2":1.4208,"party":"Conservative"},{"member":"Simon Hoare","dim1":-19.0258,"dim2":1.3646,"party":"Conservative"},{"member":"Simon Hughes","dim1":-0.1808,"dim2":0.1479,"party":"Liberal Democrat"},{"member":"Simon Kirby","dim1":-8.8299,"dim2":9.5722,"party":"Conservative"},{"member":"Simon Reevell","dim1":-0.1896,"dim2":0.1561,"party":"Conservative"},{"member":"Simon Wright","dim1":-0.2219,"dim2":0.1713,"party":"Liberal Democrat"},{"member":"Siobhain McDonagh","dim1":14.1563,"dim2":4.8859,"party":"Labour"},{"member":"Sir Alan Duncan","dim1":-17.1583,"dim2":0.1359,"party":"Conservative"},{"member":"Sir Alan Haselhurst","dim1":-9.3845,"dim2":10.2185,"party":"Conservative"},{"member":"Sir Alan Meale","dim1":5.6751,"dim2":-4.5005,"party":"Labour"},{"member":"Sir Bernard Jenkin","dim1":-2.897,"dim2":-1.8087,"party":"Conservative"},{"member":"Sir Christopher Chope","dim1":-5.4068,"dim2":-4.8313,"party":"Conservative"},{"member":"Sir David Amess","dim1":-15.5685,"dim2":6.0604,"party":"Conservative"},{"member":"Sir David Crausby","dim1":6.3848,"dim2":2.4598,"party":"Labour"},{"member":"Sir David Evennett","dim1":-3.064,"dim2":-1.8895,"party":"Conservative"},{"member":"Sir Desmond Swayne","dim1":-17.4807,"dim2":-0.7442,"party":"Conservative"},{"member":"Sir Edward Davey","dim1":8.3467,"dim2":7.9552,"party":"Liberal Democrat"},{"member":"Sir Edward Garnier","dim1":-9.4304,"dim2":10.2929,"party":"Conservative"},{"member":"Sir Edward Leigh","dim1":-18.4976,"dim2":1.653,"party":"Conservative"},{"member":"Sir Eric Pickles","dim1":-8.3874,"dim2":8.8935,"party":"Conservative"},{"member":"Sir Geoffrey Clifton-Brown","dim1":-6.1319,"dim2":-4.4098,"party":"Conservative"},{"member":"Sir Gerald Howarth","dim1":-8.0699,"dim2":8.7692,"party":"Conservative"},{"member":"Sir Gerald Kaufman","dim1":1.8786,"dim2":-1.7947,"party":"Labour"},{"member":"Sir Graham Brady","dim1":-6.2948,"dim2":-4.8925,"party":"Conservative"},{"member":"Sir Greg Knight","dim1":-18.6022,"dim2":1.0473,"party":"Conservative"},{"member":"Sir Henry Bellingham","dim1":-19.6778,"dim2":1.9486,"party":"Conservative"},{"member":"Sir Hugo  Swire","dim1":-4.6297,"dim2":4.746,"party":"Conservative"},{"member":"Sir Hugo Swire","dim1":-10.0623,"dim2":-7.3459,"party":"Conservative"},{"member":"Sir Jeffrey M. Donaldson","dim1":-11.8056,"dim2":-4.8785,"party":"Democratic Unionist Party"},{"member":"Sir Julian Brazier","dim1":-3.703,"dim2":3.7774,"party":"Conservative"},{"member":"Sir Kevin Barron","dim1":11.5883,"dim2":6.7983,"party":"Labour"},{"member":"Sir Mark Hendrick","dim1":3.42,"dim2":3.3908,"party":"Labour"},{"member":"Sir Michael Fallon","dim1":-13.3786,"dim2":-1.8431,"party":"Conservative"},{"member":"Sir Mike  Penning","dim1":-2.8522,"dim2":-2.3471,"party":"Conservative"},{"member":"Sir Mike Penning","dim1":-6.1152,"dim2":-4.4634,"party":"Conservative"},{"member":"Sir Nicholas Soames","dim1":-18.0413,"dim2":0.9775,"party":"Conservative"},{"member":"Sir Oliver Heald","dim1":-19.6127,"dim2":2.6541,"party":"Conservative"},{"member":"Sir Oliver Letwin","dim1":-15.6151,"dim2":-2.7486,"party":"Conservative"},{"member":"Sir Patrick McLoughlin","dim1":-14.4811,"dim2":-3.6463,"party":"Conservative"},{"member":"Sir Paul Beresford","dim1":-19.1979,"dim2":2.8204,"party":"Conservative"},{"member":"Sir Peter Bottomley","dim1":-17.153,"dim2":0.6655,"party":"Conservative"},{"member":"Sir Robert Syms","dim1":-9.4566,"dim2":-7.2764,"party":"Conservative"},{"member":"Sir Roger Gale","dim1":-14.7535,"dim2":0.4627,"party":"Conservative"},{"member":"Sir Simon Burns","dim1":-9.418,"dim2":10.314,"party":"Conservative"},{"member":"Sir Vince Cable","dim1":7.4568,"dim2":6.7073,"party":"Liberal Democrat"},{"member":"Sir William Cash","dim1":-19.1349,"dim2":1.2414,"party":"Conservative"},{"member":"Stella Creasy","dim1":17.8409,"dim2":1.5215,"party":"Labour"},{"member":"Stephanie Peacock","dim1":8.7017,"dim2":8.7263,"party":"Labour"},{"member":"Stephen Barclay","dim1":-19.6049,"dim2":1.4992,"party":"Conservative"},{"member":"Stephen Crabb","dim1":-19.1625,"dim2":2.1163,"party":"Conservative"},{"member":"Stephen Dorrell","dim1":-0.0322,"dim2":0.0821,"party":"Conservative"},{"member":"Stephen Doughty","dim1":16.7693,"dim2":1.9431,"party":"Labour"},{"member":"Stephen Gethins","dim1":14.7957,"dim2":0.182,"party":"Scottish National Party"},{"member":"Stephen Gilbert","dim1":0.109,"dim2":-0.0101,"party":"Liberal Democrat"},{"member":"Stephen Hammond","dim1":-18.4712,"dim2":2.4407,"party":"Conservative"},{"member":"Stephen Hepburn","dim1":0.1951,"dim2":-0.0761,"party":"Labour"},{"member":"Stephen Kerr","dim1":-10.2351,"dim2":-7.9465,"party":"Conservative"},{"member":"Stephen Kinnock","dim1":15.7743,"dim2":3.6927,"party":"Labour"},{"member":"Stephen Lloyd","dim1":6.8389,"dim2":6.9152,"party":"Liberal Democrat"},{"member":"Stephen McCabe","dim1":0.2384,"dim2":-0.1093,"party":"Labour"},{"member":"Stephen McPartland","dim1":-15.852,"dim2":1.0258,"party":"Conservative"},{"member":"Stephen Metcalfe","dim1":-20.2749,"dim2":2.8319,"party":"Conservative"},{"member":"Stephen Morgan","dim1":9.06,"dim2":8.8775,"party":"Labour"},{"member":"Stephen Mosley","dim1":-0.2528,"dim2":0.1751,"party":"Conservative"},{"member":"Stephen O'Brien","dim1":-0.1466,"dim2":0.1328,"party":"Conservative"},{"member":"Stephen Phillips","dim1":-4.7906,"dim2":5.4686,"party":"Conservative"},{"member":"Stephen Pound","dim1":15.8104,"dim2":3.1001,"party":"Labour"},{"member":"Stephen Timms","dim1":17.5329,"dim2":2.2647,"party":"Labour"},{"member":"Stephen Twigg","dim1":16.1746,"dim2":3.2675,"party":"Labour"},{"member":"Stephen Williams","dim1":-0.1401,"dim2":0.1287,"party":"Liberal Democrat"},{"member":"Steve Baker","dim1":-0.1789,"dim2":0.148,"party":"Conservative"},{"member":"Steve Brine","dim1":-18.7674,"dim2":1.3113,"party":"Conservative"},{"member":"Steve Double","dim1":-19.9393,"dim2":1.9736,"party":"Conservative"},{"member":"Steve McCabe","dim1":14.5828,"dim2":1.3765,"party":"Labour"},{"member":"Steve Reed","dim1":0.2384,"dim2":-0.1093,"party":"Labour"},{"member":"Steve Rotheram","dim1":7.3755,"dim2":-5.986,"party":"Labour"},{"member":"Steven Paterson","dim1":7.1572,"dim2":-7.7587,"party":"Scottish National Party"},{"member":"Steven Webb","dim1":-0.2219,"dim2":0.1713,"party":"Liberal Democrat"},{"member":"Stewart Hosie","dim1":14.66,"dim2":-0.2378,"party":"Scottish National Party"},{"member":"Stewart Jackson","dim1":-0.0852,"dim2":0.0814,"party":"Conservative"},{"member":"Stewart Malcolm McDonald","dim1":13.2421,"dim2":0.8505,"party":"Scottish National Party"},{"member":"Stuart Andrew","dim1":-18.03,"dim2":5.0344,"party":"Conservative"},{"member":"Stuart Blair Donaldson","dim1":6.5364,"dim2":-7.1223,"party":"Scottish National Party"},{"member":"Stuart C. McDonald","dim1":16.2414,"dim2":-0.3488,"party":"Scottish National Party"},{"member":"Sue Hayman","dim1":13.8094,"dim2":4.0219,"party":"Labour"},{"member":"Suella Braverman","dim1":-4.1957,"dim2":-2.898,"party":"Conservative"},{"member":"Suella Fernandes","dim1":-15.9346,"dim2":5.2549,"party":"Conservative"},{"member":"Susan Elan Jones","dim1":16.4516,"dim2":2.8538,"party":"Labour"},{"member":"Susan Jones","dim1":0.2384,"dim2":-0.1093,"party":"Labour"},{"member":"Sylvia Hermon","dim1":0.109,"dim2":-0.0101,"party":"Independent"},{"member":"Teresa Pearce","dim1":15.95,"dim2":2.5491,"party":"Labour"},{"member":"Tessa Jowell","dim1":0.2384,"dim2":-0.1093,"party":"Labour"},{"member":"Tessa Munt","dim1":-0.1199,"dim2":0.1331,"party":"Liberal Democrat"},{"member":"Thangam Debbonaire","dim1":9.36,"dim2":3.355,"party":"Labour"},{"member":"Thelma Walker","dim1":9.3365,"dim2":9.228,"party":"Labour"},{"member":"Theresa May","dim1":-0.1449,"dim2":0.1285,"party":"Conservative"},{"member":"Theresa Villiers","dim1":-10.659,"dim2":-7.8319,"party":"Conservative"},{"member":"Therese Coffey","dim1":-0.2373,"dim2":0.1732,"party":"Conservative"},{"member":"Thomas  Docherty","dim1":0.2384,"dim2":-0.1093,"party":"Labour"},{"member":"Thomas Brake","dim1":-0.1395,"dim2":0.1218,"party":"Liberal Democrat"},{"member":"Thomas Clarke","dim1":0.2384,"dim2":-0.1093,"party":"Labour"},{"member":"Thomas Cunningham","dim1":0.2384,"dim2":-0.1093,"party":"Labour"},{"member":"Thomas Harris","dim1":0.2384,"dim2":-0.1093,"party":"Labour"},{"member":"Thomas Watson","dim1":0.2384,"dim2":-0.1093,"party":"Labour"},{"member":"Tim Farron","dim1":10.748,"dim2":1.4543,"party":"Liberal Democrat"},{"member":"Tim Loughton","dim1":-18.6827,"dim2":2.0109,"party":"Conservative"},{"member":"Timothy Farron","dim1":-0.0733,"dim2":0.1055,"party":"Liberal Democrat"},{"member":"Timothy Loughton","dim1":-0.2528,"dim2":0.1751,"party":"Conservative"},{"member":"Timothy Yeo","dim1":-0.1896,"dim2":0.1561,"party":"Conservative"},{"member":"Tobias Ellwood","dim1":-0.2306,"dim2":0.1796,"party":"Conservative"},{"member":"Toby Perkins","dim1":15.9227,"dim2":3.7841,"party":"Labour"},{"member":"Tom Blenkinsop","dim1":7.5542,"dim2":-6.1103,"party":"Labour"},{"member":"Tom Brake","dim1":14.3089,"dim2":1.2946,"party":"Liberal Democrat"},{"member":"Tom Elliott","dim1":-1.8269,"dim2":2.6389,"party":"Ulster Unionist Party"},{"member":"Tom Greatrex","dim1":0.2384,"dim2":-0.1093,"party":"Labour"},{"member":"Tom Pursglove","dim1":-20.3624,"dim2":2.5426,"party":"Conservative"},{"member":"Tom Tugendhat","dim1":-18.6709,"dim2":2.5739,"party":"Conservative"},{"member":"Tom Watson","dim1":11.9383,"dim2":3.6864,"party":"Labour"},{"member":"Tommy Sheppard","dim1":15.283,"dim2":-0.6838,"party":"Scottish National Party"},{"member":"Tonia Antoniazzi","dim1":9.1385,"dim2":9.0186,"party":"Labour"},{"member":"Tony Lloyd","dim1":9.1638,"dim2":9.0828,"party":"Labour"},{"member":"Tracey Crouch","dim1":-17.0414,"dim2":-1.0261,"party":"Conservative"},{"member":"Tracy Brabin","dim1":12.5728,"dim2":6.8313,"party":"Labour"},{"member":"Tristram Hunt","dim1":4.8688,"dim2":-4.1952,"party":"Labour"},{"member":"Trudy Harrison","dim1":-11.4537,"dim2":-7.1718,"party":"Conservative"},{"member":"Tulip Siddiq","dim1":12.466,"dim2":2.7298,"party":"Labour"},{"member":"Valerie Vaz","dim1":17.2673,"dim2":2.8348,"party":"Labour"},{"member":"Vernon Coaker","dim1":16.4432,"dim2":2.5249,"party":"Labour"},{"member":"Vicky Ford","dim1":-9.9575,"dim2":-7.6399,"party":"Conservative"},{"member":"Vicky Foxcroft","dim1":12.5034,"dim2":1.6591,"party":"Labour"},{"member":"Victoria Atkins","dim1":-19.7423,"dim2":2.2948,"party":"Conservative"},{"member":"Victoria Borwick","dim1":-9.0015,"dim2":9.6866,"party":"Conservative"},{"member":"Victoria Prentis","dim1":-19.863,"dim2":2.0781,"party":"Conservative"},{"member":"Virendra Sharma","dim1":0.2384,"dim2":-0.1093,"party":"Labour"},{"member":"Walter Campbell","dim1":-0.0322,"dim2":0.0821,"party":"Liberal Democrat"},{"member":"Wayne David","dim1":16.195,"dim2":3.7664,"party":"Labour"},{"member":"Wendy Morton","dim1":-20.0178,"dim2":2.7573,"party":"Conservative"},{"member":"Wera Hobhouse","dim1":8.7695,"dim2":8.2643,"party":"Liberal Democrat"},{"member":"Wes Streeting","dim1":16.5561,"dim2":3.3567,"party":"Labour"},{"member":"Will Quince","dim1":-20.3196,"dim2":2.4594,"party":"Conservative"},{"member":"William Cash","dim1":-0.183,"dim2":0.1521,"party":"Conservative"},{"member":"William Clappison","dim1":-0.0322,"dim2":0.0821,"party":"Conservative"},{"member":"William Hague","dim1":-0.2528,"dim2":0.1751,"party":"Conservative"},{"member":"William Wiggin","dim1":-0.1808,"dim2":0.1479,"party":"Conservative"},{"member":"William Wragg","dim1":-9.0913,"dim2":10.0212,"party":"Conservative"},{"member":"Willie Bain","dim1":0.2384,"dim2":-0.1093,"party":"Labour"},{"member":"Wyvill Raynsford","dim1":0.2163,"dim2":-0.1138,"party":"Labour"},{"member":"Yasmin  Qureshi","dim1":0.2384,"dim2":-0.1093,"party":"Labour"},{"member":"Yasmin Qureshi","dim1":14.7338,"dim2":2.5377,"party":"Labour"},{"member":"Yvette Cooper","dim1":16.4336,"dim2":2.8869,"party":"Labour"},{"member":"Yvonne Fovargue","dim1":15.515,"dim2":2.055,"party":"Labour"},{"member":"Zac Goldsmith","dim1":-12.0886,"dim2":-5.2755,"party":"Conservative"}]
